{"version":3,"kind":"Article","sha256":"10abc0fa29463b4e14215ac2327fa5c2b83993de5b2fe7c5c9bb7b062359ef36","slug":"slides.slides01","location":"/slides/slides01.md","dependencies":[],"frontmatter":{"title":"Introduction & Motivation","content_includes_title":false,"authors":[{"id":"LH","nameParsed":{"literal":"Luca Heltai","given":"Luca","family":"Heltai"},"name":"Luca Heltai","orcid":"0000-0001-5514-4683","email":"luca.heltai@unipi.it","affiliations":["unipi"],"github":"luca-heltai","linkedin":"https://www.linkedin.com/in/heltai/","youtube":"UCK0glvtKYmVPJbpurdlt9pw","corresponding":true}],"github":"https://github.com/luca-heltai/nmopt","copyright":"2025","affiliations":[{"id":"unipi","name":"University of Pisa","department":"Department of Mathematics","address":"Largo Bruno Pontecorvo 5, 56127 Pisa, Italy","city":"Pisa","postal_code":"56127","country":"Italy","ror":"https://ror.org/03ad39j10","phone":"+39 050 221 3824"}],"numbering":{"title":{"offset":1}},"source_url":"https://github.com/luca-heltai/nmopt/blob/main/jupyterbook/slides/slides01.md","edit_url":"https://github.com/luca-heltai/nmopt/edit/main/jupyterbook/slides/slides01.md","thumbnail":"/nmopt//build/01_reduced_cost_1d-0cafe14677adb20f3a30299397d30331.png","exports":[{"format":"md","filename":"slides01.md","url":"/nmopt//build/slides01-a25528d6653c55e03abc26fd74d073cc.md"}]},"mdast":{"type":"root","children":[{"type":"block","children":[{"type":"paragraph","position":{"start":{"line":3,"column":1},"end":{"line":3,"column":1}},"children":[{"type":"text","value":"Numerical Methods for Optimal Control (NMOPT)","position":{"start":{"line":3,"column":1},"end":{"line":3,"column":1}},"key":"nw2rqK9hFh"}],"key":"h8yJiptA4k"},{"type":"paragraph","position":{"start":{"line":5,"column":1},"end":{"line":5,"column":1}},"children":[{"type":"text","value":"Luca Heltai (","position":{"start":{"line":5,"column":1},"end":{"line":5,"column":1}},"key":"yol0V4kKNd"},{"type":"link","url":"mailto:luca.heltai@unipi.it","position":{"start":{"line":5,"column":1},"end":{"line":5,"column":1}},"children":[{"type":"text","value":"luca​.heltai@unipi​.it","position":{"start":{"line":5,"column":1},"end":{"line":5,"column":1}},"key":"a8jEX5G931"}],"urlSource":"mailto:luca.heltai@unipi.it","key":"xQCqaEiFnM"},{"type":"text","value":")","position":{"start":{"line":5,"column":1},"end":{"line":5,"column":1}},"key":"YIee0GAfsB"}],"key":"ZKijlgu7IJ"},{"type":"thematicBreak","position":{"start":{"line":7,"column":1},"end":{"line":7,"column":1}},"key":"xu8LQJmnHO"},{"type":"heading","depth":2,"position":{"start":{"line":9,"column":1},"end":{"line":9,"column":1}},"children":[{"type":"text","value":"What Is Optimal Control?","position":{"start":{"line":9,"column":1},"end":{"line":9,"column":1}},"key":"ZhuzKVkX7G"}],"identifier":"what-is-optimal-control","label":"What Is Optimal Control?","html_id":"what-is-optimal-control","implicit":true,"key":"SRZGfpPDnT"},{"type":"list","ordered":false,"spread":false,"position":{"start":{"line":11,"column":1},"end":{"line":14,"column":1}},"children":[{"type":"listItem","spread":true,"position":{"start":{"line":11,"column":1},"end":{"line":11,"column":1}},"children":[{"type":"paragraph","children":[{"type":"text","value":"Choose a control ","position":{"start":{"line":11,"column":1},"end":{"line":11,"column":1}},"key":"yHrH84DFXf"},{"type":"inlineMath","value":"u","position":{"start":{"line":11,"column":1},"end":{"line":11,"column":1}},"html":"<span class=\"katex\"><span class=\"katex-mathml\"><math xmlns=\"http://www.w3.org/1998/Math/MathML\"><semantics><mrow><mi>u</mi></mrow><annotation encoding=\"application/x-tex\">u</annotation></semantics></math></span><span class=\"katex-html\" aria-hidden=\"true\"><span class=\"base\"><span class=\"strut\" style=\"height:0.4306em;\"></span><span class=\"mord mathnormal\">u</span></span></span></span>","key":"AOGXKbzakH"},{"type":"text","value":" to minimize a cost ","position":{"start":{"line":11,"column":1},"end":{"line":11,"column":1}},"key":"ZvAcmdXf7b"},{"type":"inlineMath","value":"J(y,u)","position":{"start":{"line":11,"column":1},"end":{"line":11,"column":1}},"html":"<span class=\"katex\"><span class=\"katex-mathml\"><math xmlns=\"http://www.w3.org/1998/Math/MathML\"><semantics><mrow><mi>J</mi><mo stretchy=\"false\">(</mo><mi>y</mi><mo separator=\"true\">,</mo><mi>u</mi><mo stretchy=\"false\">)</mo></mrow><annotation encoding=\"application/x-tex\">J(y,u)</annotation></semantics></math></span><span class=\"katex-html\" aria-hidden=\"true\"><span class=\"base\"><span class=\"strut\" style=\"height:1em;vertical-align:-0.25em;\"></span><span class=\"mord mathnormal\" style=\"margin-right:0.09618em;\">J</span><span class=\"mopen\">(</span><span class=\"mord mathnormal\" style=\"margin-right:0.03588em;\">y</span><span class=\"mpunct\">,</span><span class=\"mspace\" style=\"margin-right:0.1667em;\"></span><span class=\"mord mathnormal\">u</span><span class=\"mclose\">)</span></span></span></span>","key":"M3bhOSV8bA"},{"type":"text","value":".","position":{"start":{"line":11,"column":1},"end":{"line":11,"column":1}},"key":"PlEeAVSkhq"}],"key":"LYrVzF0YA9"}],"key":"Zd5VNdWnTe"},{"type":"listItem","spread":true,"position":{"start":{"line":12,"column":1},"end":{"line":12,"column":1}},"children":[{"type":"paragraph","children":[{"type":"text","value":"The state ","position":{"start":{"line":12,"column":1},"end":{"line":12,"column":1}},"key":"yXFHS6aVkA"},{"type":"inlineMath","value":"y","position":{"start":{"line":12,"column":1},"end":{"line":12,"column":1}},"html":"<span class=\"katex\"><span class=\"katex-mathml\"><math xmlns=\"http://www.w3.org/1998/Math/MathML\"><semantics><mrow><mi>y</mi></mrow><annotation encoding=\"application/x-tex\">y</annotation></semantics></math></span><span class=\"katex-html\" aria-hidden=\"true\"><span class=\"base\"><span class=\"strut\" style=\"height:0.625em;vertical-align:-0.1944em;\"></span><span class=\"mord mathnormal\" style=\"margin-right:0.03588em;\">y</span></span></span></span>","key":"AFnI3tggv7"},{"type":"text","value":" is constrained by a model (often a PDE).","position":{"start":{"line":12,"column":1},"end":{"line":12,"column":1}},"key":"UoEws9hT9T"}],"key":"shcOsxErnh"}],"key":"WNA2OsHdWM"},{"type":"listItem","spread":true,"position":{"start":{"line":13,"column":1},"end":{"line":14,"column":1}},"children":[{"type":"paragraph","children":[{"type":"text","value":"Optimization + differential constraints = PDE-constrained optimization.","position":{"start":{"line":13,"column":1},"end":{"line":13,"column":1}},"key":"ING6BzK3h0"}],"key":"FeaGt2R2SJ"}],"key":"qPJE6sY9yo"}],"key":"ky6tWfkeHM"},{"type":"thematicBreak","position":{"start":{"line":15,"column":1},"end":{"line":15,"column":1}},"key":"BBbw87ZNtq"},{"type":"heading","depth":2,"position":{"start":{"line":17,"column":1},"end":{"line":17,"column":1}},"children":[{"type":"text","value":"Abstract Formulation","position":{"start":{"line":17,"column":1},"end":{"line":17,"column":1}},"key":"sQ0QMWyLw7"}],"identifier":"abstract-formulation","label":"Abstract Formulation","html_id":"abstract-formulation","implicit":true,"key":"vv1WRxZDIH"},{"type":"paragraph","position":{"start":{"line":19,"column":1},"end":{"line":26,"column":1}},"children":[{"type":"text","value":"Minimize","position":{"start":{"line":19,"column":1},"end":{"line":19,"column":1}},"key":"Gom2UYXj0H"}],"key":"SiKwfvdTeA"},{"type":"math","value":"\\min_{y,u} \\; J(y,u)","position":{"start":{"line":19,"column":1},"end":{"line":19,"column":1}},"tight":true,"html":"<span class=\"katex-display\"><span class=\"katex\"><span class=\"katex-mathml\"><math xmlns=\"http://www.w3.org/1998/Math/MathML\" display=\"block\"><semantics><mrow><munder><mrow><mi>min</mi><mo>⁡</mo></mrow><mrow><mi>y</mi><mo separator=\"true\">,</mo><mi>u</mi></mrow></munder><mtext>  </mtext><mi>J</mi><mo stretchy=\"false\">(</mo><mi>y</mi><mo separator=\"true\">,</mo><mi>u</mi><mo stretchy=\"false\">)</mo></mrow><annotation encoding=\"application/x-tex\">\\min_{y,u} \\; J(y,u)</annotation></semantics></math></span><span class=\"katex-html\" aria-hidden=\"true\"><span class=\"base\"><span class=\"strut\" style=\"height:1.5861em;vertical-align:-0.8361em;\"></span><span class=\"mop op-limits\"><span class=\"vlist-t vlist-t2\"><span class=\"vlist-r\"><span class=\"vlist\" style=\"height:0.6679em;\"><span style=\"top:-2.4em;margin-left:0em;\"><span class=\"pstrut\" style=\"height:3em;\"></span><span class=\"sizing reset-size6 size3 mtight\"><span class=\"mord mtight\"><span class=\"mord mathnormal mtight\" style=\"margin-right:0.03588em;\">y</span><span class=\"mpunct mtight\">,</span><span class=\"mord mathnormal mtight\">u</span></span></span></span><span style=\"top:-3em;\"><span class=\"pstrut\" style=\"height:3em;\"></span><span><span class=\"mop\">min</span></span></span></span><span class=\"vlist-s\">​</span></span><span class=\"vlist-r\"><span class=\"vlist\" style=\"height:0.8361em;\"><span></span></span></span></span></span><span class=\"mspace\" style=\"margin-right:0.2778em;\"></span><span class=\"mspace\" style=\"margin-right:0.1667em;\"></span><span class=\"mord mathnormal\" style=\"margin-right:0.09618em;\">J</span><span class=\"mopen\">(</span><span class=\"mord mathnormal\" style=\"margin-right:0.03588em;\">y</span><span class=\"mpunct\">,</span><span class=\"mspace\" style=\"margin-right:0.1667em;\"></span><span class=\"mord mathnormal\">u</span><span class=\"mclose\">)</span></span></span></span></span>","enumerator":"1","key":"cvyGcGZg6f"},{"type":"paragraph","position":{"start":{"line":19,"column":1},"end":{"line":26,"column":1}},"children":[{"type":"text","value":"subject to the state equation","position":{"start":{"line":19,"column":1},"end":{"line":19,"column":1}},"key":"Nwoie3Tmhp"}],"key":"kGAbu7gVGP"},{"type":"math","value":"\\mathcal{E}(y,u) = 0.","position":{"start":{"line":19,"column":1},"end":{"line":19,"column":1}},"tight":"before","html":"<span class=\"katex-display\"><span class=\"katex\"><span class=\"katex-mathml\"><math xmlns=\"http://www.w3.org/1998/Math/MathML\" display=\"block\"><semantics><mrow><mi mathvariant=\"script\">E</mi><mo stretchy=\"false\">(</mo><mi>y</mi><mo separator=\"true\">,</mo><mi>u</mi><mo stretchy=\"false\">)</mo><mo>=</mo><mn>0.</mn></mrow><annotation encoding=\"application/x-tex\">\\mathcal{E}(y,u) = 0.</annotation></semantics></math></span><span class=\"katex-html\" aria-hidden=\"true\"><span class=\"base\"><span class=\"strut\" style=\"height:1em;vertical-align:-0.25em;\"></span><span class=\"mord mathcal\" style=\"margin-right:0.08944em;\">E</span><span class=\"mopen\">(</span><span class=\"mord mathnormal\" style=\"margin-right:0.03588em;\">y</span><span class=\"mpunct\">,</span><span class=\"mspace\" style=\"margin-right:0.1667em;\"></span><span class=\"mord mathnormal\">u</span><span class=\"mclose\">)</span><span class=\"mspace\" style=\"margin-right:0.2778em;\"></span><span class=\"mrel\">=</span><span class=\"mspace\" style=\"margin-right:0.2778em;\"></span></span><span class=\"base\"><span class=\"strut\" style=\"height:0.6444em;\"></span><span class=\"mord\">0.</span></span></span></span></span>","enumerator":"2","key":"QHadsmQqmD"},{"type":"paragraph","position":{"start":{"line":28,"column":1},"end":{"line":28,"column":1}},"children":[{"type":"text","value":"Typical pieces:","position":{"start":{"line":28,"column":1},"end":{"line":28,"column":1}},"key":"T9LChxXX7q"}],"key":"ppqNwY8VQm"},{"type":"list","ordered":false,"spread":false,"position":{"start":{"line":30,"column":1},"end":{"line":33,"column":1}},"children":[{"type":"listItem","spread":true,"position":{"start":{"line":30,"column":1},"end":{"line":30,"column":1}},"children":[{"type":"paragraph","children":[{"type":"text","value":"state equation (PDE)","position":{"start":{"line":30,"column":1},"end":{"line":30,"column":1}},"key":"d7wM1XmENc"}],"key":"QS72IxqZ85"}],"key":"roIPqn50vZ"},{"type":"listItem","spread":true,"position":{"start":{"line":31,"column":1},"end":{"line":31,"column":1}},"children":[{"type":"paragraph","children":[{"type":"text","value":"admissible controls ","position":{"start":{"line":31,"column":1},"end":{"line":31,"column":1}},"key":"NA1O9cUs7m"},{"type":"inlineMath","value":"u \\in \\mathcal{U}_{\\mathrm{ad}}","position":{"start":{"line":31,"column":1},"end":{"line":31,"column":1}},"html":"<span class=\"katex\"><span class=\"katex-mathml\"><math xmlns=\"http://www.w3.org/1998/Math/MathML\"><semantics><mrow><mi>u</mi><mo>∈</mo><msub><mi mathvariant=\"script\">U</mi><mrow><mi mathvariant=\"normal\">a</mi><mi mathvariant=\"normal\">d</mi></mrow></msub></mrow><annotation encoding=\"application/x-tex\">u \\in \\mathcal{U}_{\\mathrm{ad}}</annotation></semantics></math></span><span class=\"katex-html\" aria-hidden=\"true\"><span class=\"base\"><span class=\"strut\" style=\"height:0.5782em;vertical-align:-0.0391em;\"></span><span class=\"mord mathnormal\">u</span><span class=\"mspace\" style=\"margin-right:0.2778em;\"></span><span class=\"mrel\">∈</span><span class=\"mspace\" style=\"margin-right:0.2778em;\"></span></span><span class=\"base\"><span class=\"strut\" style=\"height:0.8333em;vertical-align:-0.15em;\"></span><span class=\"mord\"><span class=\"mord mathcal\" style=\"margin-right:0.09931em;\">U</span><span class=\"msupsub\"><span class=\"vlist-t vlist-t2\"><span class=\"vlist-r\"><span class=\"vlist\" style=\"height:0.3361em;\"><span style=\"top:-2.55em;margin-left:-0.0993em;margin-right:0.05em;\"><span class=\"pstrut\" style=\"height:2.7em;\"></span><span class=\"sizing reset-size6 size3 mtight\"><span class=\"mord mtight\"><span class=\"mord mtight\"><span class=\"mord mathrm mtight\">ad</span></span></span></span></span></span><span class=\"vlist-s\">​</span></span><span class=\"vlist-r\"><span class=\"vlist\" style=\"height:0.15em;\"><span></span></span></span></span></span></span></span></span></span>","key":"LKfubBduwA"}],"key":"JNQqulKLVy"}],"key":"CyG8JJ4tSd"},{"type":"listItem","spread":true,"position":{"start":{"line":32,"column":1},"end":{"line":33,"column":1}},"children":[{"type":"paragraph","children":[{"type":"text","value":"constraints (box constraints, etc.)","position":{"start":{"line":32,"column":1},"end":{"line":32,"column":1}},"key":"x7SadcjDFX"}],"key":"DEmVKrGt9v"}],"key":"v3GgEZXKMZ"}],"key":"NvhK7YUvLN"},{"type":"thematicBreak","position":{"start":{"line":34,"column":1},"end":{"line":34,"column":1}},"key":"UidbmQGdhF"},{"type":"heading","depth":2,"position":{"start":{"line":36,"column":1},"end":{"line":36,"column":1}},"children":[{"type":"text","value":"Forward vs Optimal Control","position":{"start":{"line":36,"column":1},"end":{"line":36,"column":1}},"key":"L3QOclmdVi"}],"identifier":"forward-vs-optimal-control","label":"Forward vs Optimal Control","html_id":"forward-vs-optimal-control","implicit":true,"key":"qpOdXw3E9q"},{"type":"list","ordered":false,"spread":false,"position":{"start":{"line":38,"column":1},"end":{"line":44,"column":1}},"children":[{"type":"listItem","spread":true,"position":{"start":{"line":38,"column":1},"end":{"line":40,"column":1}},"children":[{"type":"paragraph","children":[{"type":"text","value":"Forward (direct) problem:","position":{"start":{"line":38,"column":1},"end":{"line":38,"column":1}},"key":"PiYnb9XekW"}],"key":"Wi5SZOwXtG"},{"type":"list","ordered":false,"spread":false,"position":{"start":{"line":39,"column":1},"end":{"line":40,"column":1}},"children":[{"type":"listItem","spread":true,"position":{"start":{"line":39,"column":1},"end":{"line":39,"column":1}},"children":[{"type":"paragraph","children":[{"type":"text","value":"input data given","position":{"start":{"line":39,"column":1},"end":{"line":39,"column":1}},"key":"mAtmKG9eJt"}],"key":"Fbz0gJ5bR6"}],"key":"fQBT1Q6kSF"},{"type":"listItem","spread":true,"position":{"start":{"line":40,"column":1},"end":{"line":40,"column":1}},"children":[{"type":"paragraph","children":[{"type":"text","value":"solve PDE once to compute ","position":{"start":{"line":40,"column":1},"end":{"line":40,"column":1}},"key":"j0RgF9ZL05"},{"type":"inlineMath","value":"y","position":{"start":{"line":40,"column":1},"end":{"line":40,"column":1}},"html":"<span class=\"katex\"><span class=\"katex-mathml\"><math xmlns=\"http://www.w3.org/1998/Math/MathML\"><semantics><mrow><mi>y</mi></mrow><annotation encoding=\"application/x-tex\">y</annotation></semantics></math></span><span class=\"katex-html\" aria-hidden=\"true\"><span class=\"base\"><span class=\"strut\" style=\"height:0.625em;vertical-align:-0.1944em;\"></span><span class=\"mord mathnormal\" style=\"margin-right:0.03588em;\">y</span></span></span></span>","key":"weQrfOd5VW"}],"key":"JsMD4N7y2K"}],"key":"rqjPUDVdCF"}],"key":"nL9KKCHkM1"}],"key":"MVXTNlKhjp"},{"type":"listItem","spread":true,"position":{"start":{"line":41,"column":1},"end":{"line":44,"column":1}},"children":[{"type":"paragraph","children":[{"type":"text","value":"Optimal control:","position":{"start":{"line":41,"column":1},"end":{"line":41,"column":1}},"key":"ZFiFgzSO5r"}],"key":"j97eo4WmkZ"},{"type":"list","ordered":false,"spread":false,"position":{"start":{"line":42,"column":1},"end":{"line":44,"column":1}},"children":[{"type":"listItem","spread":true,"position":{"start":{"line":42,"column":1},"end":{"line":42,"column":1}},"children":[{"type":"paragraph","children":[{"type":"text","value":"control ","position":{"start":{"line":42,"column":1},"end":{"line":42,"column":1}},"key":"VbLBK73iVj"},{"type":"inlineMath","value":"u","position":{"start":{"line":42,"column":1},"end":{"line":42,"column":1}},"html":"<span class=\"katex\"><span class=\"katex-mathml\"><math xmlns=\"http://www.w3.org/1998/Math/MathML\"><semantics><mrow><mi>u</mi></mrow><annotation encoding=\"application/x-tex\">u</annotation></semantics></math></span><span class=\"katex-html\" aria-hidden=\"true\"><span class=\"base\"><span class=\"strut\" style=\"height:0.4306em;\"></span><span class=\"mord mathnormal\">u</span></span></span></span>","key":"wxVkMVn2g2"},{"type":"text","value":" unknown","position":{"start":{"line":42,"column":1},"end":{"line":42,"column":1}},"key":"f7wMoM1mK4"}],"key":"HIsCBrGruV"}],"key":"hceYw9jLbe"},{"type":"listItem","spread":true,"position":{"start":{"line":43,"column":1},"end":{"line":44,"column":1}},"children":[{"type":"paragraph","children":[{"type":"text","value":"PDE is solved repeatedly while optimizing ","position":{"start":{"line":43,"column":1},"end":{"line":43,"column":1}},"key":"vnv6UGmXCv"},{"type":"inlineMath","value":"J","position":{"start":{"line":43,"column":1},"end":{"line":43,"column":1}},"html":"<span class=\"katex\"><span class=\"katex-mathml\"><math xmlns=\"http://www.w3.org/1998/Math/MathML\"><semantics><mrow><mi>J</mi></mrow><annotation encoding=\"application/x-tex\">J</annotation></semantics></math></span><span class=\"katex-html\" aria-hidden=\"true\"><span class=\"base\"><span class=\"strut\" style=\"height:0.6833em;\"></span><span class=\"mord mathnormal\" style=\"margin-right:0.09618em;\">J</span></span></span></span>","key":"qazl5hBj28"}],"key":"vBZHuARFVR"}],"key":"JS579DjvOZ"}],"key":"cnjPNcwxXS"}],"key":"IMaelwyJWg"}],"key":"nSBkw8i1WL"},{"type":"paragraph","position":{"start":{"line":45,"column":1},"end":{"line":45,"column":1}},"children":[{"type":"text","value":"Key point: the PDE is a ","position":{"start":{"line":45,"column":1},"end":{"line":45,"column":1}},"key":"Kk5ffALUyZ"},{"type":"emphasis","position":{"start":{"line":45,"column":1},"end":{"line":45,"column":1}},"children":[{"type":"text","value":"constraint","position":{"start":{"line":45,"column":1},"end":{"line":45,"column":1}},"key":"QESHVLEJiv"}],"key":"gjBftjA95F"},{"type":"text","value":", not the objective.","position":{"start":{"line":45,"column":1},"end":{"line":45,"column":1}},"key":"NpnqnEU4rw"}],"key":"K4VMEzP9Bn"},{"type":"thematicBreak","position":{"start":{"line":47,"column":1},"end":{"line":47,"column":1}},"key":"VSpDPI0Vk3"},{"type":"heading","depth":2,"position":{"start":{"line":49,"column":1},"end":{"line":49,"column":1}},"children":[{"type":"text","value":"Reduced Formulation","position":{"start":{"line":49,"column":1},"end":{"line":49,"column":1}},"key":"Kqj2cWZu3k"}],"identifier":"reduced-formulation","label":"Reduced Formulation","html_id":"reduced-formulation","implicit":true,"key":"vmzJspywL4"},{"type":"paragraph","position":{"start":{"line":51,"column":1},"end":{"line":62,"column":1}},"children":[{"type":"text","value":"If the state equation defines a control-to-state map ","position":{"start":{"line":51,"column":1},"end":{"line":51,"column":1}},"key":"vwl48o15rI"},{"type":"inlineMath","value":"S","position":{"start":{"line":51,"column":1},"end":{"line":51,"column":1}},"html":"<span class=\"katex\"><span class=\"katex-mathml\"><math xmlns=\"http://www.w3.org/1998/Math/MathML\"><semantics><mrow><mi>S</mi></mrow><annotation encoding=\"application/x-tex\">S</annotation></semantics></math></span><span class=\"katex-html\" aria-hidden=\"true\"><span class=\"base\"><span class=\"strut\" style=\"height:0.6833em;\"></span><span class=\"mord mathnormal\" style=\"margin-right:0.05764em;\">S</span></span></span></span>","key":"KWeNTDqUPP"},{"type":"text","value":":","position":{"start":{"line":51,"column":1},"end":{"line":51,"column":1}},"key":"lNbUGueQri"}],"key":"yY6XQRwxIi"},{"type":"math","value":"y = S(u),","position":{"start":{"line":51,"column":1},"end":{"line":51,"column":1}},"tight":true,"html":"<span class=\"katex-display\"><span class=\"katex\"><span class=\"katex-mathml\"><math xmlns=\"http://www.w3.org/1998/Math/MathML\" display=\"block\"><semantics><mrow><mi>y</mi><mo>=</mo><mi>S</mi><mo stretchy=\"false\">(</mo><mi>u</mi><mo stretchy=\"false\">)</mo><mo separator=\"true\">,</mo></mrow><annotation encoding=\"application/x-tex\">y = S(u),</annotation></semantics></math></span><span class=\"katex-html\" aria-hidden=\"true\"><span class=\"base\"><span class=\"strut\" style=\"height:0.625em;vertical-align:-0.1944em;\"></span><span class=\"mord mathnormal\" style=\"margin-right:0.03588em;\">y</span><span class=\"mspace\" style=\"margin-right:0.2778em;\"></span><span class=\"mrel\">=</span><span class=\"mspace\" style=\"margin-right:0.2778em;\"></span></span><span class=\"base\"><span class=\"strut\" style=\"height:1em;vertical-align:-0.25em;\"></span><span class=\"mord mathnormal\" style=\"margin-right:0.05764em;\">S</span><span class=\"mopen\">(</span><span class=\"mord mathnormal\">u</span><span class=\"mclose\">)</span><span class=\"mpunct\">,</span></span></span></span></span>","enumerator":"3","key":"iowVriS1rO"},{"type":"paragraph","position":{"start":{"line":51,"column":1},"end":{"line":62,"column":1}},"children":[{"type":"text","value":"then define the reduced cost","position":{"start":{"line":51,"column":1},"end":{"line":51,"column":1}},"key":"zNvjYwgVFN"}],"key":"XlKxZcabBZ"},{"type":"math","value":"f(u) := J(S(u),u),","position":{"start":{"line":51,"column":1},"end":{"line":51,"column":1}},"tight":true,"html":"<span class=\"katex-display\"><span class=\"katex\"><span class=\"katex-mathml\"><math xmlns=\"http://www.w3.org/1998/Math/MathML\" display=\"block\"><semantics><mrow><mi>f</mi><mo stretchy=\"false\">(</mo><mi>u</mi><mo stretchy=\"false\">)</mo><mo>:</mo><mo>=</mo><mi>J</mi><mo stretchy=\"false\">(</mo><mi>S</mi><mo stretchy=\"false\">(</mo><mi>u</mi><mo stretchy=\"false\">)</mo><mo separator=\"true\">,</mo><mi>u</mi><mo stretchy=\"false\">)</mo><mo separator=\"true\">,</mo></mrow><annotation encoding=\"application/x-tex\">f(u) := J(S(u),u),</annotation></semantics></math></span><span class=\"katex-html\" aria-hidden=\"true\"><span class=\"base\"><span class=\"strut\" style=\"height:1em;vertical-align:-0.25em;\"></span><span class=\"mord mathnormal\" style=\"margin-right:0.10764em;\">f</span><span class=\"mopen\">(</span><span class=\"mord mathnormal\">u</span><span class=\"mclose\">)</span><span class=\"mspace\" style=\"margin-right:0.2778em;\"></span><span class=\"mrel\">:=</span><span class=\"mspace\" style=\"margin-right:0.2778em;\"></span></span><span class=\"base\"><span class=\"strut\" style=\"height:1em;vertical-align:-0.25em;\"></span><span class=\"mord mathnormal\" style=\"margin-right:0.09618em;\">J</span><span class=\"mopen\">(</span><span class=\"mord mathnormal\" style=\"margin-right:0.05764em;\">S</span><span class=\"mopen\">(</span><span class=\"mord mathnormal\">u</span><span class=\"mclose\">)</span><span class=\"mpunct\">,</span><span class=\"mspace\" style=\"margin-right:0.1667em;\"></span><span class=\"mord mathnormal\">u</span><span class=\"mclose\">)</span><span class=\"mpunct\">,</span></span></span></span></span>","enumerator":"4","key":"rIKjc0tPgA"},{"type":"paragraph","position":{"start":{"line":51,"column":1},"end":{"line":62,"column":1}},"children":[{"type":"text","value":"and solve","position":{"start":{"line":51,"column":1},"end":{"line":51,"column":1}},"key":"JbMmGpJKTz"}],"key":"jF6a5bD1YQ"},{"type":"math","value":"\\min_{u} f(u).","position":{"start":{"line":51,"column":1},"end":{"line":51,"column":1}},"tight":"before","html":"<span class=\"katex-display\"><span class=\"katex\"><span class=\"katex-mathml\"><math xmlns=\"http://www.w3.org/1998/Math/MathML\" display=\"block\"><semantics><mrow><munder><mrow><mi>min</mi><mo>⁡</mo></mrow><mi>u</mi></munder><mi>f</mi><mo stretchy=\"false\">(</mo><mi>u</mi><mo stretchy=\"false\">)</mo><mi mathvariant=\"normal\">.</mi></mrow><annotation encoding=\"application/x-tex\">\\min_{u} f(u).</annotation></semantics></math></span><span class=\"katex-html\" aria-hidden=\"true\"><span class=\"base\"><span class=\"strut\" style=\"height:1.45em;vertical-align:-0.7em;\"></span><span class=\"mop op-limits\"><span class=\"vlist-t vlist-t2\"><span class=\"vlist-r\"><span class=\"vlist\" style=\"height:0.6679em;\"><span style=\"top:-2.4em;margin-left:0em;\"><span class=\"pstrut\" style=\"height:3em;\"></span><span class=\"sizing reset-size6 size3 mtight\"><span class=\"mord mtight\"><span class=\"mord mathnormal mtight\">u</span></span></span></span><span style=\"top:-3em;\"><span class=\"pstrut\" style=\"height:3em;\"></span><span><span class=\"mop\">min</span></span></span></span><span class=\"vlist-s\">​</span></span><span class=\"vlist-r\"><span class=\"vlist\" style=\"height:0.7em;\"><span></span></span></span></span></span><span class=\"mspace\" style=\"margin-right:0.1667em;\"></span><span class=\"mord mathnormal\" style=\"margin-right:0.10764em;\">f</span><span class=\"mopen\">(</span><span class=\"mord mathnormal\">u</span><span class=\"mclose\">)</span><span class=\"mord\">.</span></span></span></span></span>","enumerator":"5","key":"hLSrltHBoY"},{"type":"paragraph","position":{"start":{"line":64,"column":1},"end":{"line":64,"column":1}},"children":[{"type":"text","value":"Why it matters:","position":{"start":{"line":64,"column":1},"end":{"line":64,"column":1}},"key":"xPSRunFdI8"}],"key":"AhUQa9MBvn"},{"type":"list","ordered":false,"spread":false,"position":{"start":{"line":66,"column":1},"end":{"line":68,"column":1}},"children":[{"type":"listItem","spread":true,"position":{"start":{"line":66,"column":1},"end":{"line":66,"column":1}},"children":[{"type":"paragraph","children":[{"type":"text","value":"separates “PDE solve” from “optimization step”","position":{"start":{"line":66,"column":1},"end":{"line":66,"column":1}},"key":"T2PUJRYcRJ"}],"key":"xiNpYBAHFI"}],"key":"uuPQCQTgah"},{"type":"listItem","spread":true,"position":{"start":{"line":67,"column":1},"end":{"line":68,"column":1}},"children":[{"type":"paragraph","children":[{"type":"text","value":"makes gradients/adjoins systematic","position":{"start":{"line":67,"column":1},"end":{"line":67,"column":1}},"key":"Z0vZtuzZXn"}],"key":"IQ0PDdD3Rz"}],"key":"GUj41bhA5c"}],"key":"fnaDYXmROP"},{"type":"thematicBreak","position":{"start":{"line":69,"column":1},"end":{"line":69,"column":1}},"key":"dhpDVpUyTs"},{"type":"heading","depth":2,"position":{"start":{"line":71,"column":1},"end":{"line":71,"column":1}},"children":[{"type":"text","value":"Tiny Example Notebook","position":{"start":{"line":71,"column":1},"end":{"line":71,"column":1}},"key":"QRRehriu83"}],"identifier":"tiny-example-notebook","label":"Tiny Example Notebook","html_id":"tiny-example-notebook","implicit":true,"key":"yjjdpXDkGh"},{"type":"list","ordered":false,"spread":false,"position":{"start":{"line":73,"column":1},"end":{"line":75,"column":1}},"children":[{"type":"listItem","spread":true,"position":{"start":{"line":73,"column":1},"end":{"line":73,"column":1}},"children":[{"type":"paragraph","children":[{"type":"text","value":"Finite-dimensional LQ reduction + a 1D slice plot.","position":{"start":{"line":73,"column":1},"end":{"line":73,"column":1}},"key":"G5muFJsksI"}],"key":"GibafTxfsT"}],"key":"CO9HojzDCv"},{"type":"listItem","spread":true,"position":{"start":{"line":74,"column":1},"end":{"line":75,"column":1}},"children":[{"type":"paragraph","children":[{"type":"text","value":"Generates figures used in these slides.","position":{"start":{"line":74,"column":1},"end":{"line":74,"column":1}},"key":"ANMXqYV6fI"}],"key":"D43HgKY3iZ"}],"key":"eOmpPvfsin"}],"key":"GyTyQL1kVF"},{"type":"paragraph","position":{"start":{"line":76,"column":1},"end":{"line":76,"column":1}},"children":[{"type":"text","value":"File: ","position":{"start":{"line":76,"column":1},"end":{"line":76,"column":1}},"key":"lANTeTz9Gm"},{"type":"inlineCode","value":"codes/lecture01/finite_dim_analogy.ipynb","position":{"start":{"line":76,"column":1},"end":{"line":76,"column":1}},"key":"l9AOsg93J3"}],"key":"DXyvDkM3jj"},{"type":"thematicBreak","position":{"start":{"line":78,"column":1},"end":{"line":78,"column":1}},"key":"aJ4w9fk6z4"},{"type":"heading","depth":2,"position":{"start":{"line":80,"column":1},"end":{"line":80,"column":1}},"children":[{"type":"text","value":"Example: Reduced Cost Shape","position":{"start":{"line":80,"column":1},"end":{"line":80,"column":1}},"key":"TFQ5pzq9RD"}],"identifier":"example-reduced-cost-shape","label":"Example: Reduced Cost Shape","html_id":"example-reduced-cost-shape","implicit":true,"key":"bpc552XswP"},{"type":"image","url":"/nmopt//build/01_reduced_cost_1d-0cafe14677adb20f3a30299397d30331.png","alt":"Reduced cost in 1D","position":{"start":{"line":82,"column":1},"end":{"line":82,"column":1}},"key":"U031Ylwloe","urlSource":"assets/01_reduced_cost_1d.png"},{"type":"thematicBreak","position":{"start":{"line":84,"column":1},"end":{"line":84,"column":1}},"key":"RnnIEUShyj"},{"type":"heading","depth":2,"position":{"start":{"line":86,"column":1},"end":{"line":86,"column":1}},"children":[{"type":"text","value":"Control-to-State Pipeline","position":{"start":{"line":86,"column":1},"end":{"line":86,"column":1}},"key":"IrM25Nszmi"}],"identifier":"control-to-state-pipeline","label":"Control-to-State Pipeline","html_id":"control-to-state-pipeline","implicit":true,"key":"zJUGz4BvIN"},{"type":"image","url":"/nmopt//build/01_control_to_state-eff9951b9956bd066ca5fba00d6fe291.png","alt":"Control-to-state diagram","position":{"start":{"line":88,"column":1},"end":{"line":88,"column":1}},"key":"CJL3yBeoMj","urlSource":"assets/01_control_to_state.png"},{"type":"thematicBreak","position":{"start":{"line":90,"column":1},"end":{"line":90,"column":1}},"key":"c73P7yQx4U"},{"type":"heading","depth":2,"position":{"start":{"line":92,"column":1},"end":{"line":92,"column":1}},"children":[{"type":"text","value":"A Finite-Dimensional Analogy","position":{"start":{"line":92,"column":1},"end":{"line":92,"column":1}},"key":"e6yRxtaiyC"}],"identifier":"a-finite-dimensional-analogy","label":"A Finite-Dimensional Analogy","html_id":"a-finite-dimensional-analogy","implicit":true,"key":"DvTitSNLan"},{"type":"paragraph","position":{"start":{"line":94,"column":1},"end":{"line":101,"column":1}},"children":[{"type":"text","value":"Given ","position":{"start":{"line":94,"column":1},"end":{"line":94,"column":1}},"key":"d1z4HMyOJ4"},{"type":"inlineMath","value":"A y = B u","position":{"start":{"line":94,"column":1},"end":{"line":94,"column":1}},"html":"<span class=\"katex\"><span class=\"katex-mathml\"><math xmlns=\"http://www.w3.org/1998/Math/MathML\"><semantics><mrow><mi>A</mi><mi>y</mi><mo>=</mo><mi>B</mi><mi>u</mi></mrow><annotation encoding=\"application/x-tex\">A y = B u</annotation></semantics></math></span><span class=\"katex-html\" aria-hidden=\"true\"><span class=\"base\"><span class=\"strut\" style=\"height:0.8778em;vertical-align:-0.1944em;\"></span><span class=\"mord mathnormal\">A</span><span class=\"mord mathnormal\" style=\"margin-right:0.03588em;\">y</span><span class=\"mspace\" style=\"margin-right:0.2778em;\"></span><span class=\"mrel\">=</span><span class=\"mspace\" style=\"margin-right:0.2778em;\"></span></span><span class=\"base\"><span class=\"strut\" style=\"height:0.6833em;\"></span><span class=\"mord mathnormal\" style=\"margin-right:0.05017em;\">B</span><span class=\"mord mathnormal\">u</span></span></span></span>","key":"Zgi4b1ONsN"},{"type":"text","value":" with invertible ","position":{"start":{"line":94,"column":1},"end":{"line":94,"column":1}},"key":"hO6cGt4X4W"},{"type":"inlineMath","value":"A","position":{"start":{"line":94,"column":1},"end":{"line":94,"column":1}},"html":"<span class=\"katex\"><span class=\"katex-mathml\"><math xmlns=\"http://www.w3.org/1998/Math/MathML\"><semantics><mrow><mi>A</mi></mrow><annotation encoding=\"application/x-tex\">A</annotation></semantics></math></span><span class=\"katex-html\" aria-hidden=\"true\"><span class=\"base\"><span class=\"strut\" style=\"height:0.6833em;\"></span><span class=\"mord mathnormal\">A</span></span></span></span>","key":"TMadQwgm96"},{"type":"text","value":":","position":{"start":{"line":94,"column":1},"end":{"line":94,"column":1}},"key":"nHfJLstPSm"}],"key":"mIagtTTp67"},{"type":"math","value":"y = A^{-1} B u =: S u","position":{"start":{"line":94,"column":1},"end":{"line":94,"column":1}},"tight":true,"html":"<span class=\"katex-display\"><span class=\"katex\"><span class=\"katex-mathml\"><math xmlns=\"http://www.w3.org/1998/Math/MathML\" display=\"block\"><semantics><mrow><mi>y</mi><mo>=</mo><msup><mi>A</mi><mrow><mo>−</mo><mn>1</mn></mrow></msup><mi>B</mi><mi>u</mi><mo>=</mo><mo>:</mo><mi>S</mi><mi>u</mi></mrow><annotation encoding=\"application/x-tex\">y = A^{-1} B u =: S u</annotation></semantics></math></span><span class=\"katex-html\" aria-hidden=\"true\"><span class=\"base\"><span class=\"strut\" style=\"height:0.625em;vertical-align:-0.1944em;\"></span><span class=\"mord mathnormal\" style=\"margin-right:0.03588em;\">y</span><span class=\"mspace\" style=\"margin-right:0.2778em;\"></span><span class=\"mrel\">=</span><span class=\"mspace\" style=\"margin-right:0.2778em;\"></span></span><span class=\"base\"><span class=\"strut\" style=\"height:0.8641em;\"></span><span class=\"mord\"><span class=\"mord mathnormal\">A</span><span class=\"msupsub\"><span class=\"vlist-t\"><span class=\"vlist-r\"><span class=\"vlist\" style=\"height:0.8641em;\"><span style=\"top:-3.113em;margin-right:0.05em;\"><span class=\"pstrut\" style=\"height:2.7em;\"></span><span class=\"sizing reset-size6 size3 mtight\"><span class=\"mord mtight\"><span class=\"mord mtight\">−</span><span class=\"mord mtight\">1</span></span></span></span></span></span></span></span></span><span class=\"mord mathnormal\" style=\"margin-right:0.05017em;\">B</span><span class=\"mord mathnormal\">u</span><span class=\"mspace\" style=\"margin-right:0.2778em;\"></span><span class=\"mrel\">=:</span><span class=\"mspace\" style=\"margin-right:0.2778em;\"></span></span><span class=\"base\"><span class=\"strut\" style=\"height:0.6833em;\"></span><span class=\"mord mathnormal\" style=\"margin-right:0.05764em;\">S</span><span class=\"mord mathnormal\">u</span></span></span></span></span>","enumerator":"6","key":"J7WKFgwlJq"},{"type":"paragraph","position":{"start":{"line":94,"column":1},"end":{"line":101,"column":1}},"children":[{"type":"text","value":"Reduced problem:","position":{"start":{"line":94,"column":1},"end":{"line":94,"column":1}},"key":"bIvoGvC7n1"}],"key":"VqsTqpGC0g"},{"type":"math","value":"\\min_u f(u) := J(Su,u).","position":{"start":{"line":94,"column":1},"end":{"line":94,"column":1}},"tight":"before","html":"<span class=\"katex-display\"><span class=\"katex\"><span class=\"katex-mathml\"><math xmlns=\"http://www.w3.org/1998/Math/MathML\" display=\"block\"><semantics><mrow><munder><mrow><mi>min</mi><mo>⁡</mo></mrow><mi>u</mi></munder><mi>f</mi><mo stretchy=\"false\">(</mo><mi>u</mi><mo stretchy=\"false\">)</mo><mo>:</mo><mo>=</mo><mi>J</mi><mo stretchy=\"false\">(</mo><mi>S</mi><mi>u</mi><mo separator=\"true\">,</mo><mi>u</mi><mo stretchy=\"false\">)</mo><mi mathvariant=\"normal\">.</mi></mrow><annotation encoding=\"application/x-tex\">\\min_u f(u) := J(Su,u).</annotation></semantics></math></span><span class=\"katex-html\" aria-hidden=\"true\"><span class=\"base\"><span class=\"strut\" style=\"height:1.45em;vertical-align:-0.7em;\"></span><span class=\"mop op-limits\"><span class=\"vlist-t vlist-t2\"><span class=\"vlist-r\"><span class=\"vlist\" style=\"height:0.6679em;\"><span style=\"top:-2.4em;margin-left:0em;\"><span class=\"pstrut\" style=\"height:3em;\"></span><span class=\"sizing reset-size6 size3 mtight\"><span class=\"mord mathnormal mtight\">u</span></span></span><span style=\"top:-3em;\"><span class=\"pstrut\" style=\"height:3em;\"></span><span><span class=\"mop\">min</span></span></span></span><span class=\"vlist-s\">​</span></span><span class=\"vlist-r\"><span class=\"vlist\" style=\"height:0.7em;\"><span></span></span></span></span></span><span class=\"mspace\" style=\"margin-right:0.1667em;\"></span><span class=\"mord mathnormal\" style=\"margin-right:0.10764em;\">f</span><span class=\"mopen\">(</span><span class=\"mord mathnormal\">u</span><span class=\"mclose\">)</span><span class=\"mspace\" style=\"margin-right:0.2778em;\"></span><span class=\"mrel\">:=</span><span class=\"mspace\" style=\"margin-right:0.2778em;\"></span></span><span class=\"base\"><span class=\"strut\" style=\"height:1em;vertical-align:-0.25em;\"></span><span class=\"mord mathnormal\" style=\"margin-right:0.09618em;\">J</span><span class=\"mopen\">(</span><span class=\"mord mathnormal\" style=\"margin-right:0.05764em;\">S</span><span class=\"mord mathnormal\">u</span><span class=\"mpunct\">,</span><span class=\"mspace\" style=\"margin-right:0.1667em;\"></span><span class=\"mord mathnormal\">u</span><span class=\"mclose\">)</span><span class=\"mord\">.</span></span></span></span></span>","enumerator":"7","key":"ahLwG5dyry"},{"type":"paragraph","position":{"start":{"line":103,"column":1},"end":{"line":103,"column":1}},"children":[{"type":"text","value":"This is the template we will reuse in infinite dimensions.","position":{"start":{"line":103,"column":1},"end":{"line":103,"column":1}},"key":"wHuLGUWV1g"}],"key":"ymZTXWbpUs"},{"type":"thematicBreak","position":{"start":{"line":105,"column":1},"end":{"line":105,"column":1}},"key":"m3DTdRROmH"},{"type":"heading","depth":2,"position":{"start":{"line":107,"column":1},"end":{"line":107,"column":1}},"children":[{"type":"text","value":"Constrained Minimization in 2D","position":{"start":{"line":107,"column":1},"end":{"line":107,"column":1}},"key":"EvPpuLRPFk"}],"identifier":"constrained-minimization-in-2d","label":"Constrained Minimization in 2D","html_id":"constrained-minimization-in-2d","implicit":true,"key":"M0eaBQcYba"},{"type":"paragraph","position":{"start":{"line":109,"column":1},"end":{"line":115,"column":1}},"children":[{"type":"text","value":"Consider","position":{"start":{"line":109,"column":1},"end":{"line":109,"column":1}},"key":"vmgU3BYCEN"}],"key":"CNE5EUKEZT"},{"type":"math","value":"\\min_{u\\in\\mathbb{R}^2} f(u)=\\frac12 u^T A u\n\\quad \\text{s.t.} \\quad\n\\varphi(u)=Bu-g=0,","position":{"start":{"line":109,"column":1},"end":{"line":109,"column":1}},"tight":true,"html":"<span class=\"katex-display\"><span class=\"katex\"><span class=\"katex-mathml\"><math xmlns=\"http://www.w3.org/1998/Math/MathML\" display=\"block\"><semantics><mrow><munder><mrow><mi>min</mi><mo>⁡</mo></mrow><mrow><mi>u</mi><mo>∈</mo><msup><mi mathvariant=\"double-struck\">R</mi><mn>2</mn></msup></mrow></munder><mi>f</mi><mo stretchy=\"false\">(</mo><mi>u</mi><mo stretchy=\"false\">)</mo><mo>=</mo><mfrac><mn>1</mn><mn>2</mn></mfrac><msup><mi>u</mi><mi>T</mi></msup><mi>A</mi><mi>u</mi><mspace width=\"1em\"/><mtext>s.t.</mtext><mspace width=\"1em\"/><mi>φ</mi><mo stretchy=\"false\">(</mo><mi>u</mi><mo stretchy=\"false\">)</mo><mo>=</mo><mi>B</mi><mi>u</mi><mo>−</mo><mi>g</mi><mo>=</mo><mn>0</mn><mo separator=\"true\">,</mo></mrow><annotation encoding=\"application/x-tex\">\\min_{u\\in\\mathbb{R}^2} f(u)=\\frac12 u^T A u\n\\quad \\text{s.t.} \\quad\n\\varphi(u)=Bu-g=0,</annotation></semantics></math></span><span class=\"katex-html\" aria-hidden=\"true\"><span class=\"base\"><span class=\"strut\" style=\"height:1.5658em;vertical-align:-0.8158em;\"></span><span class=\"mop op-limits\"><span class=\"vlist-t vlist-t2\"><span class=\"vlist-r\"><span class=\"vlist\" style=\"height:0.6679em;\"><span style=\"top:-2.3116em;margin-left:0em;\"><span class=\"pstrut\" style=\"height:3em;\"></span><span class=\"sizing reset-size6 size3 mtight\"><span class=\"mord mtight\"><span class=\"mord mathnormal mtight\">u</span><span class=\"mrel mtight\">∈</span><span class=\"mord mtight\"><span class=\"mord mathbb mtight\">R</span><span class=\"msupsub\"><span class=\"vlist-t\"><span class=\"vlist-r\"><span class=\"vlist\" style=\"height:0.7463em;\"><span style=\"top:-2.786em;margin-right:0.0714em;\"><span class=\"pstrut\" style=\"height:2.5em;\"></span><span class=\"sizing reset-size3 size1 mtight\"><span class=\"mord mtight\">2</span></span></span></span></span></span></span></span></span></span></span><span style=\"top:-3em;\"><span class=\"pstrut\" style=\"height:3em;\"></span><span><span class=\"mop\">min</span></span></span></span><span class=\"vlist-s\">​</span></span><span class=\"vlist-r\"><span class=\"vlist\" style=\"height:0.8158em;\"><span></span></span></span></span></span><span class=\"mspace\" style=\"margin-right:0.1667em;\"></span><span class=\"mord mathnormal\" style=\"margin-right:0.10764em;\">f</span><span class=\"mopen\">(</span><span class=\"mord mathnormal\">u</span><span class=\"mclose\">)</span><span class=\"mspace\" style=\"margin-right:0.2778em;\"></span><span class=\"mrel\">=</span><span class=\"mspace\" style=\"margin-right:0.2778em;\"></span></span><span class=\"base\"><span class=\"strut\" style=\"height:2.0074em;vertical-align:-0.686em;\"></span><span class=\"mord\"><span class=\"mopen nulldelimiter\"></span><span class=\"mfrac\"><span class=\"vlist-t vlist-t2\"><span class=\"vlist-r\"><span class=\"vlist\" style=\"height:1.3214em;\"><span style=\"top:-2.314em;\"><span class=\"pstrut\" style=\"height:3em;\"></span><span class=\"mord\"><span class=\"mord\">2</span></span></span><span style=\"top:-3.23em;\"><span class=\"pstrut\" style=\"height:3em;\"></span><span class=\"frac-line\" style=\"border-bottom-width:0.04em;\"></span></span><span style=\"top:-3.677em;\"><span class=\"pstrut\" style=\"height:3em;\"></span><span class=\"mord\"><span class=\"mord\">1</span></span></span></span><span class=\"vlist-s\">​</span></span><span class=\"vlist-r\"><span class=\"vlist\" style=\"height:0.686em;\"><span></span></span></span></span></span><span class=\"mclose nulldelimiter\"></span></span><span class=\"mord\"><span class=\"mord mathnormal\">u</span><span class=\"msupsub\"><span class=\"vlist-t\"><span class=\"vlist-r\"><span class=\"vlist\" style=\"height:0.8913em;\"><span style=\"top:-3.113em;margin-right:0.05em;\"><span class=\"pstrut\" style=\"height:2.7em;\"></span><span class=\"sizing reset-size6 size3 mtight\"><span class=\"mord mathnormal mtight\" style=\"margin-right:0.13889em;\">T</span></span></span></span></span></span></span></span><span class=\"mord mathnormal\">A</span><span class=\"mord mathnormal\">u</span><span class=\"mspace\" style=\"margin-right:1em;\"></span><span class=\"mord text\"><span class=\"mord\">s.t.</span></span><span class=\"mspace\" style=\"margin-right:1em;\"></span><span class=\"mord mathnormal\">φ</span><span class=\"mopen\">(</span><span class=\"mord mathnormal\">u</span><span class=\"mclose\">)</span><span class=\"mspace\" style=\"margin-right:0.2778em;\"></span><span class=\"mrel\">=</span><span class=\"mspace\" style=\"margin-right:0.2778em;\"></span></span><span class=\"base\"><span class=\"strut\" style=\"height:0.7667em;vertical-align:-0.0833em;\"></span><span class=\"mord mathnormal\" style=\"margin-right:0.05017em;\">B</span><span class=\"mord mathnormal\">u</span><span class=\"mspace\" style=\"margin-right:0.2222em;\"></span><span class=\"mbin\">−</span><span class=\"mspace\" style=\"margin-right:0.2222em;\"></span></span><span class=\"base\"><span class=\"strut\" style=\"height:0.625em;vertical-align:-0.1944em;\"></span><span class=\"mord mathnormal\" style=\"margin-right:0.03588em;\">g</span><span class=\"mspace\" style=\"margin-right:0.2778em;\"></span><span class=\"mrel\">=</span><span class=\"mspace\" style=\"margin-right:0.2778em;\"></span></span><span class=\"base\"><span class=\"strut\" style=\"height:0.8389em;vertical-align:-0.1944em;\"></span><span class=\"mord\">0</span><span class=\"mpunct\">,</span></span></span></span></span>","enumerator":"8","key":"B3ngjto30R"},{"type":"paragraph","position":{"start":{"line":109,"column":1},"end":{"line":115,"column":1}},"children":[{"type":"text","value":"with ","position":{"start":{"line":109,"column":1},"end":{"line":109,"column":1}},"key":"hsyPPOD3a0"},{"type":"inlineMath","value":"A","position":{"start":{"line":109,"column":1},"end":{"line":109,"column":1}},"html":"<span class=\"katex\"><span class=\"katex-mathml\"><math xmlns=\"http://www.w3.org/1998/Math/MathML\"><semantics><mrow><mi>A</mi></mrow><annotation encoding=\"application/x-tex\">A</annotation></semantics></math></span><span class=\"katex-html\" aria-hidden=\"true\"><span class=\"base\"><span class=\"strut\" style=\"height:0.6833em;\"></span><span class=\"mord mathnormal\">A</span></span></span></span>","key":"T5FEN8SUgP"},{"type":"text","value":" SPD, ","position":{"start":{"line":109,"column":1},"end":{"line":109,"column":1}},"key":"Lle6sEEtqL"},{"type":"inlineMath","value":"B\\in\\mathbb{R}^{1\\times 2}","position":{"start":{"line":109,"column":1},"end":{"line":109,"column":1}},"html":"<span class=\"katex\"><span class=\"katex-mathml\"><math xmlns=\"http://www.w3.org/1998/Math/MathML\"><semantics><mrow><mi>B</mi><mo>∈</mo><msup><mi mathvariant=\"double-struck\">R</mi><mrow><mn>1</mn><mo>×</mo><mn>2</mn></mrow></msup></mrow><annotation encoding=\"application/x-tex\">B\\in\\mathbb{R}^{1\\times 2}</annotation></semantics></math></span><span class=\"katex-html\" aria-hidden=\"true\"><span class=\"base\"><span class=\"strut\" style=\"height:0.7224em;vertical-align:-0.0391em;\"></span><span class=\"mord mathnormal\" style=\"margin-right:0.05017em;\">B</span><span class=\"mspace\" style=\"margin-right:0.2778em;\"></span><span class=\"mrel\">∈</span><span class=\"mspace\" style=\"margin-right:0.2778em;\"></span></span><span class=\"base\"><span class=\"strut\" style=\"height:0.8141em;\"></span><span class=\"mord\"><span class=\"mord mathbb\">R</span><span class=\"msupsub\"><span class=\"vlist-t\"><span class=\"vlist-r\"><span class=\"vlist\" style=\"height:0.8141em;\"><span style=\"top:-3.063em;margin-right:0.05em;\"><span class=\"pstrut\" style=\"height:2.7em;\"></span><span class=\"sizing reset-size6 size3 mtight\"><span class=\"mord mtight\"><span class=\"mord mtight\">1</span><span class=\"mbin mtight\">×</span><span class=\"mord mtight\">2</span></span></span></span></span></span></span></span></span></span></span></span>","key":"sISfDAMemD"},{"type":"text","value":".","position":{"start":{"line":109,"column":1},"end":{"line":109,"column":1}},"key":"IKEphKWXNv"}],"key":"xDHE4VhvuC"},{"type":"paragraph","position":{"start":{"line":117,"column":1},"end":{"line":122,"column":1}},"children":[{"type":"text","value":"At an optimum:","position":{"start":{"line":117,"column":1},"end":{"line":117,"column":1}},"key":"NdZD3myUdO"}],"key":"pn7Lnksqnn"},{"type":"math","value":"\\nabla f(\\bar u)-(\\nabla\\varphi(\\bar u))^T\\lambda=0,\n\\qquad\n\\varphi(\\bar u)=0.","position":{"start":{"line":117,"column":1},"end":{"line":117,"column":1}},"tight":"before","html":"<span class=\"katex-display\"><span class=\"katex\"><span class=\"katex-mathml\"><math xmlns=\"http://www.w3.org/1998/Math/MathML\" display=\"block\"><semantics><mrow><mi mathvariant=\"normal\">∇</mi><mi>f</mi><mo stretchy=\"false\">(</mo><mover accent=\"true\"><mi>u</mi><mo>ˉ</mo></mover><mo stretchy=\"false\">)</mo><mo>−</mo><mo stretchy=\"false\">(</mo><mi mathvariant=\"normal\">∇</mi><mi>φ</mi><mo stretchy=\"false\">(</mo><mover accent=\"true\"><mi>u</mi><mo>ˉ</mo></mover><mo stretchy=\"false\">)</mo><msup><mo stretchy=\"false\">)</mo><mi>T</mi></msup><mi>λ</mi><mo>=</mo><mn>0</mn><mo separator=\"true\">,</mo><mspace width=\"2em\"/><mi>φ</mi><mo stretchy=\"false\">(</mo><mover accent=\"true\"><mi>u</mi><mo>ˉ</mo></mover><mo stretchy=\"false\">)</mo><mo>=</mo><mn>0.</mn></mrow><annotation encoding=\"application/x-tex\">\\nabla f(\\bar u)-(\\nabla\\varphi(\\bar u))^T\\lambda=0,\n\\qquad\n\\varphi(\\bar u)=0.</annotation></semantics></math></span><span class=\"katex-html\" aria-hidden=\"true\"><span class=\"base\"><span class=\"strut\" style=\"height:1em;vertical-align:-0.25em;\"></span><span class=\"mord\">∇</span><span class=\"mord mathnormal\" style=\"margin-right:0.10764em;\">f</span><span class=\"mopen\">(</span><span class=\"mord accent\"><span class=\"vlist-t\"><span class=\"vlist-r\"><span class=\"vlist\" style=\"height:0.5678em;\"><span style=\"top:-3em;\"><span class=\"pstrut\" style=\"height:3em;\"></span><span class=\"mord mathnormal\">u</span></span><span style=\"top:-3em;\"><span class=\"pstrut\" style=\"height:3em;\"></span><span class=\"accent-body\" style=\"left:-0.2222em;\"><span class=\"mord\">ˉ</span></span></span></span></span></span></span><span class=\"mclose\">)</span><span class=\"mspace\" style=\"margin-right:0.2222em;\"></span><span class=\"mbin\">−</span><span class=\"mspace\" style=\"margin-right:0.2222em;\"></span></span><span class=\"base\"><span class=\"strut\" style=\"height:1.1413em;vertical-align:-0.25em;\"></span><span class=\"mopen\">(</span><span class=\"mord\">∇</span><span class=\"mord mathnormal\">φ</span><span class=\"mopen\">(</span><span class=\"mord accent\"><span class=\"vlist-t\"><span class=\"vlist-r\"><span class=\"vlist\" style=\"height:0.5678em;\"><span style=\"top:-3em;\"><span class=\"pstrut\" style=\"height:3em;\"></span><span class=\"mord mathnormal\">u</span></span><span style=\"top:-3em;\"><span class=\"pstrut\" style=\"height:3em;\"></span><span class=\"accent-body\" style=\"left:-0.2222em;\"><span class=\"mord\">ˉ</span></span></span></span></span></span></span><span class=\"mclose\">)</span><span class=\"mclose\"><span class=\"mclose\">)</span><span class=\"msupsub\"><span class=\"vlist-t\"><span class=\"vlist-r\"><span class=\"vlist\" style=\"height:0.8913em;\"><span style=\"top:-3.113em;margin-right:0.05em;\"><span class=\"pstrut\" style=\"height:2.7em;\"></span><span class=\"sizing reset-size6 size3 mtight\"><span class=\"mord mathnormal mtight\" style=\"margin-right:0.13889em;\">T</span></span></span></span></span></span></span></span><span class=\"mord mathnormal\">λ</span><span class=\"mspace\" style=\"margin-right:0.2778em;\"></span><span class=\"mrel\">=</span><span class=\"mspace\" style=\"margin-right:0.2778em;\"></span></span><span class=\"base\"><span class=\"strut\" style=\"height:1em;vertical-align:-0.25em;\"></span><span class=\"mord\">0</span><span class=\"mpunct\">,</span><span class=\"mspace\" style=\"margin-right:2em;\"></span><span class=\"mspace\" style=\"margin-right:0.1667em;\"></span><span class=\"mord mathnormal\">φ</span><span class=\"mopen\">(</span><span class=\"mord accent\"><span class=\"vlist-t\"><span class=\"vlist-r\"><span class=\"vlist\" style=\"height:0.5678em;\"><span style=\"top:-3em;\"><span class=\"pstrut\" style=\"height:3em;\"></span><span class=\"mord mathnormal\">u</span></span><span style=\"top:-3em;\"><span class=\"pstrut\" style=\"height:3em;\"></span><span class=\"accent-body\" style=\"left:-0.2222em;\"><span class=\"mord\">ˉ</span></span></span></span></span></span></span><span class=\"mclose\">)</span><span class=\"mspace\" style=\"margin-right:0.2778em;\"></span><span class=\"mrel\">=</span><span class=\"mspace\" style=\"margin-right:0.2778em;\"></span></span><span class=\"base\"><span class=\"strut\" style=\"height:0.6444em;\"></span><span class=\"mord\">0.</span></span></span></span></span>","enumerator":"9","key":"SywAYYOmdt"},{"type":"thematicBreak","position":{"start":{"line":124,"column":1},"end":{"line":124,"column":1}},"key":"MS6Ow1PRR5"},{"type":"heading","depth":2,"position":{"start":{"line":126,"column":1},"end":{"line":126,"column":1}},"children":[{"type":"text","value":"Lagrangian and KKT System","position":{"start":{"line":126,"column":1},"end":{"line":126,"column":1}},"key":"DAw7UoNMW1"}],"identifier":"lagrangian-and-kkt-system","label":"Lagrangian and KKT System","html_id":"lagrangian-and-kkt-system","implicit":true,"key":"nWENXQnbAx"},{"type":"paragraph","position":{"start":{"line":128,"column":1},"end":{"line":131,"column":1}},"children":[{"type":"text","value":"Lagrangian:","position":{"start":{"line":128,"column":1},"end":{"line":128,"column":1}},"key":"H1fbR8Etjl"}],"key":"RMbnYtI9X1"},{"type":"math","value":"\\mathcal{L}(u,\\lambda)=f(u)-\\varphi(u)\\cdot \\lambda","position":{"start":{"line":128,"column":1},"end":{"line":128,"column":1}},"tight":"before","html":"<span class=\"katex-display\"><span class=\"katex\"><span class=\"katex-mathml\"><math xmlns=\"http://www.w3.org/1998/Math/MathML\" display=\"block\"><semantics><mrow><mi mathvariant=\"script\">L</mi><mo stretchy=\"false\">(</mo><mi>u</mi><mo separator=\"true\">,</mo><mi>λ</mi><mo stretchy=\"false\">)</mo><mo>=</mo><mi>f</mi><mo stretchy=\"false\">(</mo><mi>u</mi><mo stretchy=\"false\">)</mo><mo>−</mo><mi>φ</mi><mo stretchy=\"false\">(</mo><mi>u</mi><mo stretchy=\"false\">)</mo><mo>⋅</mo><mi>λ</mi></mrow><annotation encoding=\"application/x-tex\">\\mathcal{L}(u,\\lambda)=f(u)-\\varphi(u)\\cdot \\lambda</annotation></semantics></math></span><span class=\"katex-html\" aria-hidden=\"true\"><span class=\"base\"><span class=\"strut\" style=\"height:1em;vertical-align:-0.25em;\"></span><span class=\"mord mathcal\">L</span><span class=\"mopen\">(</span><span class=\"mord mathnormal\">u</span><span class=\"mpunct\">,</span><span class=\"mspace\" style=\"margin-right:0.1667em;\"></span><span class=\"mord mathnormal\">λ</span><span class=\"mclose\">)</span><span class=\"mspace\" style=\"margin-right:0.2778em;\"></span><span class=\"mrel\">=</span><span class=\"mspace\" style=\"margin-right:0.2778em;\"></span></span><span class=\"base\"><span class=\"strut\" style=\"height:1em;vertical-align:-0.25em;\"></span><span class=\"mord mathnormal\" style=\"margin-right:0.10764em;\">f</span><span class=\"mopen\">(</span><span class=\"mord mathnormal\">u</span><span class=\"mclose\">)</span><span class=\"mspace\" style=\"margin-right:0.2222em;\"></span><span class=\"mbin\">−</span><span class=\"mspace\" style=\"margin-right:0.2222em;\"></span></span><span class=\"base\"><span class=\"strut\" style=\"height:1em;vertical-align:-0.25em;\"></span><span class=\"mord mathnormal\">φ</span><span class=\"mopen\">(</span><span class=\"mord mathnormal\">u</span><span class=\"mclose\">)</span><span class=\"mspace\" style=\"margin-right:0.2222em;\"></span><span class=\"mbin\">⋅</span><span class=\"mspace\" style=\"margin-right:0.2222em;\"></span></span><span class=\"base\"><span class=\"strut\" style=\"height:0.6944em;\"></span><span class=\"mord mathnormal\">λ</span></span></span></span></span>","enumerator":"10","key":"Dg20UABppE"},{"type":"paragraph","position":{"start":{"line":133,"column":1},"end":{"line":137,"column":1}},"children":[{"type":"text","value":"Stationarity:","position":{"start":{"line":133,"column":1},"end":{"line":133,"column":1}},"key":"zshKEPXNBB"}],"key":"MCO2qoTLQ4"},{"type":"math","value":"\\nabla_u\\mathcal{L}=Au-B^T\\lambda=0,\\qquad\n\\nabla_\\lambda\\mathcal{L}=-Bu+g=0.","position":{"start":{"line":133,"column":1},"end":{"line":133,"column":1}},"tight":"before","html":"<span class=\"katex-display\"><span class=\"katex\"><span class=\"katex-mathml\"><math xmlns=\"http://www.w3.org/1998/Math/MathML\" display=\"block\"><semantics><mrow><msub><mi mathvariant=\"normal\">∇</mi><mi>u</mi></msub><mi mathvariant=\"script\">L</mi><mo>=</mo><mi>A</mi><mi>u</mi><mo>−</mo><msup><mi>B</mi><mi>T</mi></msup><mi>λ</mi><mo>=</mo><mn>0</mn><mo separator=\"true\">,</mo><mspace width=\"2em\"/><msub><mi mathvariant=\"normal\">∇</mi><mi>λ</mi></msub><mi mathvariant=\"script\">L</mi><mo>=</mo><mo>−</mo><mi>B</mi><mi>u</mi><mo>+</mo><mi>g</mi><mo>=</mo><mn>0.</mn></mrow><annotation encoding=\"application/x-tex\">\\nabla_u\\mathcal{L}=Au-B^T\\lambda=0,\\qquad\n\\nabla_\\lambda\\mathcal{L}=-Bu+g=0.</annotation></semantics></math></span><span class=\"katex-html\" aria-hidden=\"true\"><span class=\"base\"><span class=\"strut\" style=\"height:0.8333em;vertical-align:-0.15em;\"></span><span class=\"mord\"><span class=\"mord\">∇</span><span class=\"msupsub\"><span class=\"vlist-t vlist-t2\"><span class=\"vlist-r\"><span class=\"vlist\" style=\"height:0.1514em;\"><span style=\"top:-2.55em;margin-left:0em;margin-right:0.05em;\"><span class=\"pstrut\" style=\"height:2.7em;\"></span><span class=\"sizing reset-size6 size3 mtight\"><span class=\"mord mathnormal mtight\">u</span></span></span></span><span class=\"vlist-s\">​</span></span><span class=\"vlist-r\"><span class=\"vlist\" style=\"height:0.15em;\"><span></span></span></span></span></span></span><span class=\"mord mathcal\">L</span><span class=\"mspace\" style=\"margin-right:0.2778em;\"></span><span class=\"mrel\">=</span><span class=\"mspace\" style=\"margin-right:0.2778em;\"></span></span><span class=\"base\"><span class=\"strut\" style=\"height:0.7667em;vertical-align:-0.0833em;\"></span><span class=\"mord mathnormal\">A</span><span class=\"mord mathnormal\">u</span><span class=\"mspace\" style=\"margin-right:0.2222em;\"></span><span class=\"mbin\">−</span><span class=\"mspace\" style=\"margin-right:0.2222em;\"></span></span><span class=\"base\"><span class=\"strut\" style=\"height:0.8913em;\"></span><span class=\"mord\"><span class=\"mord mathnormal\" style=\"margin-right:0.05017em;\">B</span><span class=\"msupsub\"><span class=\"vlist-t\"><span class=\"vlist-r\"><span class=\"vlist\" style=\"height:0.8913em;\"><span style=\"top:-3.113em;margin-right:0.05em;\"><span class=\"pstrut\" style=\"height:2.7em;\"></span><span class=\"sizing reset-size6 size3 mtight\"><span class=\"mord mathnormal mtight\" style=\"margin-right:0.13889em;\">T</span></span></span></span></span></span></span></span><span class=\"mord mathnormal\">λ</span><span class=\"mspace\" style=\"margin-right:0.2778em;\"></span><span class=\"mrel\">=</span><span class=\"mspace\" style=\"margin-right:0.2778em;\"></span></span><span class=\"base\"><span class=\"strut\" style=\"height:0.8778em;vertical-align:-0.1944em;\"></span><span class=\"mord\">0</span><span class=\"mpunct\">,</span><span class=\"mspace\" style=\"margin-right:2em;\"></span><span class=\"mspace\" style=\"margin-right:0.1667em;\"></span><span class=\"mord\"><span class=\"mord\">∇</span><span class=\"msupsub\"><span class=\"vlist-t vlist-t2\"><span class=\"vlist-r\"><span class=\"vlist\" style=\"height:0.3361em;\"><span style=\"top:-2.55em;margin-left:0em;margin-right:0.05em;\"><span class=\"pstrut\" style=\"height:2.7em;\"></span><span class=\"sizing reset-size6 size3 mtight\"><span class=\"mord mathnormal mtight\">λ</span></span></span></span><span class=\"vlist-s\">​</span></span><span class=\"vlist-r\"><span class=\"vlist\" style=\"height:0.15em;\"><span></span></span></span></span></span></span><span class=\"mord mathcal\">L</span><span class=\"mspace\" style=\"margin-right:0.2778em;\"></span><span class=\"mrel\">=</span><span class=\"mspace\" style=\"margin-right:0.2778em;\"></span></span><span class=\"base\"><span class=\"strut\" style=\"height:0.7667em;vertical-align:-0.0833em;\"></span><span class=\"mord\">−</span><span class=\"mord mathnormal\" style=\"margin-right:0.05017em;\">B</span><span class=\"mord mathnormal\">u</span><span class=\"mspace\" style=\"margin-right:0.2222em;\"></span><span class=\"mbin\">+</span><span class=\"mspace\" style=\"margin-right:0.2222em;\"></span></span><span class=\"base\"><span class=\"strut\" style=\"height:0.625em;vertical-align:-0.1944em;\"></span><span class=\"mord mathnormal\" style=\"margin-right:0.03588em;\">g</span><span class=\"mspace\" style=\"margin-right:0.2778em;\"></span><span class=\"mrel\">=</span><span class=\"mspace\" style=\"margin-right:0.2778em;\"></span></span><span class=\"base\"><span class=\"strut\" style=\"height:0.6444em;\"></span><span class=\"mord\">0.</span></span></span></span></span>","enumerator":"11","key":"bf7dJKH8Lb"},{"type":"paragraph","position":{"start":{"line":139,"column":1},"end":{"line":139,"column":1}},"children":[{"type":"text","value":"Equivalent saddle-point linear system","position":{"start":{"line":139,"column":1},"end":{"line":139,"column":1}},"key":"B05VcDvqD9"}],"key":"bq6jKM0MsM"},{"type":"math","value":"\\begin{pmatrix}A & -B^T \\\\\\ -B & 0\\end{pmatrix}\\begin{pmatrix}u \\\\\\ \\lambda\\end{pmatrix}=\\begin{pmatrix}0 \\\\\\ -g\\end{pmatrix}","position":{"start":{"line":141,"column":1},"end":{"line":141,"column":1}},"html":"<span class=\"katex-display\"><span class=\"katex\"><span class=\"katex-mathml\"><math xmlns=\"http://www.w3.org/1998/Math/MathML\" display=\"block\"><semantics><mrow><mrow><mo fence=\"true\">(</mo><mtable rowspacing=\"0.16em\" columnalign=\"center center\" columnspacing=\"1em\"><mtr><mtd><mstyle scriptlevel=\"0\" displaystyle=\"false\"><mi>A</mi></mstyle></mtd><mtd><mstyle scriptlevel=\"0\" displaystyle=\"false\"><mrow><mo>−</mo><msup><mi>B</mi><mi>T</mi></msup></mrow></mstyle></mtd></mtr><mtr><mtd><mstyle scriptlevel=\"0\" displaystyle=\"false\"><mrow><mtext> </mtext><mo>−</mo><mi>B</mi></mrow></mstyle></mtd><mtd><mstyle scriptlevel=\"0\" displaystyle=\"false\"><mn>0</mn></mstyle></mtd></mtr></mtable><mo fence=\"true\">)</mo></mrow><mrow><mo fence=\"true\">(</mo><mtable rowspacing=\"0.16em\" columnalign=\"center\" columnspacing=\"1em\"><mtr><mtd><mstyle scriptlevel=\"0\" displaystyle=\"false\"><mi>u</mi></mstyle></mtd></mtr><mtr><mtd><mstyle scriptlevel=\"0\" displaystyle=\"false\"><mrow><mtext> </mtext><mi>λ</mi></mrow></mstyle></mtd></mtr></mtable><mo fence=\"true\">)</mo></mrow><mo>=</mo><mrow><mo fence=\"true\">(</mo><mtable rowspacing=\"0.16em\" columnalign=\"center\" columnspacing=\"1em\"><mtr><mtd><mstyle scriptlevel=\"0\" displaystyle=\"false\"><mn>0</mn></mstyle></mtd></mtr><mtr><mtd><mstyle scriptlevel=\"0\" displaystyle=\"false\"><mrow><mtext> </mtext><mo>−</mo><mi>g</mi></mrow></mstyle></mtd></mtr></mtable><mo fence=\"true\">)</mo></mrow></mrow><annotation encoding=\"application/x-tex\">\\begin{pmatrix}A &amp; -B^T \\\\\\ -B &amp; 0\\end{pmatrix}\\begin{pmatrix}u \\\\\\ \\lambda\\end{pmatrix}=\\begin{pmatrix}0 \\\\\\ -g\\end{pmatrix}</annotation></semantics></math></span><span class=\"katex-html\" aria-hidden=\"true\"><span class=\"base\"><span class=\"strut\" style=\"height:2.4013em;vertical-align:-0.9507em;\"></span><span class=\"minner\"><span class=\"mopen delimcenter\" style=\"top:0em;\"><span class=\"delimsizing size3\">(</span></span><span class=\"mord\"><span class=\"mtable\"><span class=\"col-align-c\"><span class=\"vlist-t vlist-t2\"><span class=\"vlist-r\"><span class=\"vlist\" style=\"height:1.4507em;\"><span style=\"top:-3.6093em;\"><span class=\"pstrut\" style=\"height:3em;\"></span><span class=\"mord\"><span class=\"mord mathnormal\">A</span></span></span><span style=\"top:-2.4093em;\"><span class=\"pstrut\" style=\"height:3em;\"></span><span class=\"mord\"><span class=\"mspace\"> </span><span class=\"mord\">−</span><span class=\"mord mathnormal\" style=\"margin-right:0.05017em;\">B</span></span></span></span><span class=\"vlist-s\">​</span></span><span class=\"vlist-r\"><span class=\"vlist\" style=\"height:0.9507em;\"><span></span></span></span></span></span><span class=\"arraycolsep\" style=\"width:0.5em;\"></span><span class=\"arraycolsep\" style=\"width:0.5em;\"></span><span class=\"col-align-c\"><span class=\"vlist-t vlist-t2\"><span class=\"vlist-r\"><span class=\"vlist\" style=\"height:1.4507em;\"><span style=\"top:-3.6093em;\"><span class=\"pstrut\" style=\"height:3em;\"></span><span class=\"mord\"><span class=\"mord\">−</span><span class=\"mord\"><span class=\"mord mathnormal\" style=\"margin-right:0.05017em;\">B</span><span class=\"msupsub\"><span class=\"vlist-t\"><span class=\"vlist-r\"><span class=\"vlist\" style=\"height:0.8413em;\"><span style=\"top:-3.063em;margin-right:0.05em;\"><span class=\"pstrut\" style=\"height:2.7em;\"></span><span class=\"sizing reset-size6 size3 mtight\"><span class=\"mord mathnormal mtight\" style=\"margin-right:0.13889em;\">T</span></span></span></span></span></span></span></span></span></span><span style=\"top:-2.4093em;\"><span class=\"pstrut\" style=\"height:3em;\"></span><span class=\"mord\"><span class=\"mord\">0</span></span></span></span><span class=\"vlist-s\">​</span></span><span class=\"vlist-r\"><span class=\"vlist\" style=\"height:0.9507em;\"><span></span></span></span></span></span></span></span><span class=\"mclose delimcenter\" style=\"top:0em;\"><span class=\"delimsizing size3\">)</span></span></span><span class=\"mspace\" style=\"margin-right:0.1667em;\"></span><span class=\"minner\"><span class=\"mopen delimcenter\" style=\"top:0em;\"><span class=\"delimsizing size3\">(</span></span><span class=\"mord\"><span class=\"mtable\"><span class=\"col-align-c\"><span class=\"vlist-t vlist-t2\"><span class=\"vlist-r\"><span class=\"vlist\" style=\"height:1.45em;\"><span style=\"top:-3.61em;\"><span class=\"pstrut\" style=\"height:3em;\"></span><span class=\"mord\"><span class=\"mord mathnormal\">u</span></span></span><span style=\"top:-2.41em;\"><span class=\"pstrut\" style=\"height:3em;\"></span><span class=\"mord\"><span class=\"mspace\"> </span><span class=\"mord mathnormal\">λ</span></span></span></span><span class=\"vlist-s\">​</span></span><span class=\"vlist-r\"><span class=\"vlist\" style=\"height:0.95em;\"><span></span></span></span></span></span></span></span><span class=\"mclose delimcenter\" style=\"top:0em;\"><span class=\"delimsizing size3\">)</span></span></span><span class=\"mspace\" style=\"margin-right:0.2778em;\"></span><span class=\"mrel\">=</span><span class=\"mspace\" style=\"margin-right:0.2778em;\"></span></span><span class=\"base\"><span class=\"strut\" style=\"height:2.4em;vertical-align:-0.95em;\"></span><span class=\"minner\"><span class=\"mopen delimcenter\" style=\"top:0em;\"><span class=\"delimsizing size3\">(</span></span><span class=\"mord\"><span class=\"mtable\"><span class=\"col-align-c\"><span class=\"vlist-t vlist-t2\"><span class=\"vlist-r\"><span class=\"vlist\" style=\"height:1.45em;\"><span style=\"top:-3.61em;\"><span class=\"pstrut\" style=\"height:3em;\"></span><span class=\"mord\"><span class=\"mord\">0</span></span></span><span style=\"top:-2.41em;\"><span class=\"pstrut\" style=\"height:3em;\"></span><span class=\"mord\"><span class=\"mspace\"> </span><span class=\"mord\">−</span><span class=\"mord mathnormal\" style=\"margin-right:0.03588em;\">g</span></span></span></span><span class=\"vlist-s\">​</span></span><span class=\"vlist-r\"><span class=\"vlist\" style=\"height:0.95em;\"><span></span></span></span></span></span></span></span><span class=\"mclose delimcenter\" style=\"top:0em;\"><span class=\"delimsizing size3\">)</span></span></span></span></span></span></span>","enumerator":"12","key":"UkOIgHSPOM"},{"type":"thematicBreak","position":{"start":{"line":143,"column":1},"end":{"line":143,"column":1}},"key":"lwzn2VVVq1"},{"type":"heading","depth":2,"position":{"start":{"line":145,"column":1},"end":{"line":145,"column":1}},"children":[{"type":"text","value":"2D Constrained Geometry","position":{"start":{"line":145,"column":1},"end":{"line":145,"column":1}},"key":"EwG1YzQfRg"}],"identifier":"id-2d-constrained-geometry","label":"2D Constrained Geometry","html_id":"id-2d-constrained-geometry","implicit":true,"key":"a6y7QG64AJ"},{"type":"image","class":"fit-figure","url":"/nmopt//build/01_minimization_geom-a7b904ac459d0b90a6a481568d92d5ce.png","alt":"2D constrained geometry","key":"wqkZtkJr8J","urlSource":"assets/01_minimization_geometry.png"},{"type":"thematicBreak","position":{"start":{"line":149,"column":1},"end":{"line":149,"column":1}},"key":"Y79Y9aoCgC"},{"type":"heading","depth":2,"position":{"start":{"line":151,"column":1},"end":{"line":151,"column":1}},"children":[{"type":"text","value":"Objective on the Feasible Line","position":{"start":{"line":151,"column":1},"end":{"line":151,"column":1}},"key":"ajUUcRrJrB"}],"identifier":"objective-on-the-feasible-line","label":"Objective on the Feasible Line","html_id":"objective-on-the-feasible-line","implicit":true,"key":"bUG3l1AlfA"},{"type":"image","class":"fit-figure","url":"/nmopt//build/01_minimization_on_c-1b7e25f9afb8444bfd0c40185c3b0d23.png","alt":"Objective restricted to the feasible set","key":"Hg2rb9yYsw","urlSource":"assets/01_minimization_on_constraint.png"},{"type":"thematicBreak","position":{"start":{"line":155,"column":1},"end":{"line":155,"column":1}},"key":"EPe9h0Fu51"},{"type":"heading","depth":2,"position":{"start":{"line":157,"column":1},"end":{"line":157,"column":1}},"children":[{"type":"text","value":"When PDEs Show Up","position":{"start":{"line":157,"column":1},"end":{"line":157,"column":1}},"key":"GBqG7pgSde"}],"identifier":"when-pdes-show-up","label":"When PDEs Show Up","html_id":"when-pdes-show-up","implicit":true,"key":"CnNllJkhph"},{"type":"paragraph","position":{"start":{"line":159,"column":1},"end":{"line":159,"column":1}},"children":[{"type":"text","value":"States: temperature, displacement, velocity, concentration, ...","position":{"start":{"line":159,"column":1},"end":{"line":159,"column":1}},"key":"fKZsBmfu06"}],"key":"ETzcvk4PI4"},{"type":"paragraph","position":{"start":{"line":161,"column":1},"end":{"line":161,"column":1}},"children":[{"type":"text","value":"Controls:","position":{"start":{"line":161,"column":1},"end":{"line":161,"column":1}},"key":"jymEQi9M6t"}],"key":"KGDFciN1YX"},{"type":"list","ordered":false,"spread":false,"position":{"start":{"line":163,"column":1},"end":{"line":167,"column":1}},"children":[{"type":"listItem","spread":true,"position":{"start":{"line":163,"column":1},"end":{"line":163,"column":1}},"children":[{"type":"paragraph","children":[{"type":"text","value":"distributed sources","position":{"start":{"line":163,"column":1},"end":{"line":163,"column":1}},"key":"pXPMr96cL6"}],"key":"OlglYzUQBH"}],"key":"TCPt61DDXY"},{"type":"listItem","spread":true,"position":{"start":{"line":164,"column":1},"end":{"line":164,"column":1}},"children":[{"type":"paragraph","children":[{"type":"text","value":"boundary inputs","position":{"start":{"line":164,"column":1},"end":{"line":164,"column":1}},"key":"rQQlsJTnnK"}],"key":"PDoiWL1ptL"}],"key":"x26CG66JQk"},{"type":"listItem","spread":true,"position":{"start":{"line":165,"column":1},"end":{"line":165,"column":1}},"children":[{"type":"paragraph","children":[{"type":"text","value":"initial conditions","position":{"start":{"line":165,"column":1},"end":{"line":165,"column":1}},"key":"Xvt07MfCbf"}],"key":"LFPTnI9ash"}],"key":"eHYCu8rjhZ"},{"type":"listItem","spread":true,"position":{"start":{"line":166,"column":1},"end":{"line":167,"column":1}},"children":[{"type":"paragraph","children":[{"type":"text","value":"parameters / coefficients","position":{"start":{"line":166,"column":1},"end":{"line":166,"column":1}},"key":"A9c1azmiCB"}],"key":"BN4yBz7DBI"}],"key":"pC9bKZQexK"}],"key":"qsGicxL2Ml"},{"type":"thematicBreak","position":{"start":{"line":168,"column":1},"end":{"line":168,"column":1}},"key":"dpzuBObFoV"},{"type":"heading","depth":2,"position":{"start":{"line":170,"column":1},"end":{"line":170,"column":1}},"children":[{"type":"text","value":"Typical Examples","position":{"start":{"line":170,"column":1},"end":{"line":170,"column":1}},"key":"fVFty7B8Y4"}],"identifier":"typical-examples","label":"Typical Examples","html_id":"typical-examples","implicit":true,"key":"aqQDsXH0RA"},{"type":"list","ordered":false,"spread":false,"position":{"start":{"line":172,"column":1},"end":{"line":176,"column":1}},"children":[{"type":"listItem","spread":true,"position":{"start":{"line":172,"column":1},"end":{"line":172,"column":1}},"children":[{"type":"paragraph","children":[{"type":"text","value":"Elliptic: stationary heating / diffusion","position":{"start":{"line":172,"column":1},"end":{"line":172,"column":1}},"key":"paNtIq2o2m"}],"key":"VGx6NYmKbh"}],"key":"riSkM87YBZ"},{"type":"listItem","spread":true,"position":{"start":{"line":173,"column":1},"end":{"line":173,"column":1}},"children":[{"type":"paragraph","children":[{"type":"text","value":"Parabolic: time-dependent heating","position":{"start":{"line":173,"column":1},"end":{"line":173,"column":1}},"key":"BrUwoq4Li7"}],"key":"xoH8KQGcCw"}],"key":"VGoHfmxRWp"},{"type":"listItem","spread":true,"position":{"start":{"line":174,"column":1},"end":{"line":174,"column":1}},"children":[{"type":"paragraph","children":[{"type":"text","value":"Nonlinear: Navier-Stokes flow control","position":{"start":{"line":174,"column":1},"end":{"line":174,"column":1}},"key":"I2LzlPDLCy"}],"key":"qZahkKS5mZ"}],"key":"tdFwvFvW2G"},{"type":"listItem","spread":true,"position":{"start":{"line":175,"column":1},"end":{"line":176,"column":1}},"children":[{"type":"paragraph","children":[{"type":"text","value":"Inverse problems: parameter estimation / data assimilation","position":{"start":{"line":175,"column":1},"end":{"line":175,"column":1}},"key":"Hp0xvgnoPp"}],"key":"ijIrcui0NM"}],"key":"zkJx0MF0rp"}],"key":"tVc5eQuI5h"},{"type":"thematicBreak","position":{"start":{"line":177,"column":1},"end":{"line":177,"column":1}},"key":"rAgWup8OMH"},{"type":"heading","depth":2,"position":{"start":{"line":179,"column":1},"end":{"line":179,"column":1}},"children":[{"type":"text","value":"Constraints","position":{"start":{"line":179,"column":1},"end":{"line":179,"column":1}},"key":"ROYji0rBuQ"}],"identifier":"constraints","label":"Constraints","html_id":"constraints","implicit":true,"key":"QgvtiPmkfI"},{"type":"paragraph","position":{"start":{"line":181,"column":1},"end":{"line":184,"column":1}},"children":[{"type":"text","value":"Common: box constraints on the control","position":{"start":{"line":181,"column":1},"end":{"line":181,"column":1}},"key":"IiezJGCO25"}],"key":"EpwSrRuXKM"},{"type":"math","value":"u_{\\min} \\le u \\le u_{\\max}.","position":{"start":{"line":181,"column":1},"end":{"line":181,"column":1}},"tight":"before","html":"<span class=\"katex-display\"><span class=\"katex\"><span class=\"katex-mathml\"><math xmlns=\"http://www.w3.org/1998/Math/MathML\" display=\"block\"><semantics><mrow><msub><mi>u</mi><mi>min</mi><mo>⁡</mo></msub><mo>≤</mo><mi>u</mi><mo>≤</mo><msub><mi>u</mi><mi>max</mi><mo>⁡</mo></msub><mi mathvariant=\"normal\">.</mi></mrow><annotation encoding=\"application/x-tex\">u_{\\min} \\le u \\le u_{\\max}.</annotation></semantics></math></span><span class=\"katex-html\" aria-hidden=\"true\"><span class=\"base\"><span class=\"strut\" style=\"height:0.786em;vertical-align:-0.15em;\"></span><span class=\"mord\"><span class=\"mord mathnormal\">u</span><span class=\"msupsub\"><span class=\"vlist-t vlist-t2\"><span class=\"vlist-r\"><span class=\"vlist\" style=\"height:0.3175em;\"><span style=\"top:-2.55em;margin-left:0em;margin-right:0.05em;\"><span class=\"pstrut\" style=\"height:2.7em;\"></span><span class=\"sizing reset-size6 size3 mtight\"><span class=\"mord mtight\"><span class=\"mop mtight\"><span class=\"mtight\">m</span><span class=\"mtight\">i</span><span class=\"mtight\">n</span></span></span></span></span></span><span class=\"vlist-s\">​</span></span><span class=\"vlist-r\"><span class=\"vlist\" style=\"height:0.15em;\"><span></span></span></span></span></span></span><span class=\"mspace\" style=\"margin-right:0.2778em;\"></span><span class=\"mrel\">≤</span><span class=\"mspace\" style=\"margin-right:0.2778em;\"></span></span><span class=\"base\"><span class=\"strut\" style=\"height:0.7719em;vertical-align:-0.136em;\"></span><span class=\"mord mathnormal\">u</span><span class=\"mspace\" style=\"margin-right:0.2778em;\"></span><span class=\"mrel\">≤</span><span class=\"mspace\" style=\"margin-right:0.2778em;\"></span></span><span class=\"base\"><span class=\"strut\" style=\"height:0.5806em;vertical-align:-0.15em;\"></span><span class=\"mord\"><span class=\"mord mathnormal\">u</span><span class=\"msupsub\"><span class=\"vlist-t vlist-t2\"><span class=\"vlist-r\"><span class=\"vlist\" style=\"height:0.1514em;\"><span style=\"top:-2.55em;margin-left:0em;margin-right:0.05em;\"><span class=\"pstrut\" style=\"height:2.7em;\"></span><span class=\"sizing reset-size6 size3 mtight\"><span class=\"mord mtight\"><span class=\"mop mtight\"><span class=\"mtight\">m</span><span class=\"mtight\">a</span><span class=\"mtight\">x</span></span></span></span></span></span><span class=\"vlist-s\">​</span></span><span class=\"vlist-r\"><span class=\"vlist\" style=\"height:0.15em;\"><span></span></span></span></span></span></span><span class=\"mord\">.</span></span></span></span></span>","enumerator":"13","key":"TlSfY7bm5w"},{"type":"paragraph","position":{"start":{"line":186,"column":1},"end":{"line":186,"column":1}},"children":[{"type":"text","value":"Leads to:","position":{"start":{"line":186,"column":1},"end":{"line":186,"column":1}},"key":"BV3UvPoxfO"}],"key":"d9EXqviEFX"},{"type":"list","ordered":false,"spread":false,"position":{"start":{"line":188,"column":1},"end":{"line":191,"column":1}},"children":[{"type":"listItem","spread":true,"position":{"start":{"line":188,"column":1},"end":{"line":188,"column":1}},"children":[{"type":"paragraph","children":[{"type":"text","value":"variational inequalities","position":{"start":{"line":188,"column":1},"end":{"line":188,"column":1}},"key":"KtNSWGCXkB"}],"key":"HRzzpthblA"}],"key":"JcbCm54V1V"},{"type":"listItem","spread":true,"position":{"start":{"line":189,"column":1},"end":{"line":189,"column":1}},"children":[{"type":"paragraph","children":[{"type":"text","value":"KKT conditions","position":{"start":{"line":189,"column":1},"end":{"line":189,"column":1}},"key":"uUls0OGxIt"}],"key":"FVKGGcnaJf"}],"key":"IWdFYC4FED"},{"type":"listItem","spread":true,"position":{"start":{"line":190,"column":1},"end":{"line":191,"column":1}},"children":[{"type":"paragraph","children":[{"type":"text","value":"active-set / projection-type algorithms","position":{"start":{"line":190,"column":1},"end":{"line":190,"column":1}},"key":"TV8tZL7ezL"}],"key":"DtW3dIZTDV"}],"key":"ONWq5mUMyQ"}],"key":"igCzr3MCFF"},{"type":"thematicBreak","position":{"start":{"line":192,"column":1},"end":{"line":192,"column":1}},"key":"M6Y5K4fRhQ"},{"type":"heading","depth":2,"position":{"start":{"line":194,"column":1},"end":{"line":194,"column":1}},"children":[{"type":"text","value":"Typical OCP Variations","position":{"start":{"line":194,"column":1},"end":{"line":194,"column":1}},"key":"gIyqkp9Jco"}],"identifier":"typical-ocp-variations","label":"Typical OCP Variations","html_id":"typical-ocp-variations","implicit":true,"key":"c1fj0wbjjX"},{"type":"list","ordered":false,"spread":false,"position":{"start":{"line":196,"column":1},"end":{"line":203,"column":1}},"children":[{"type":"listItem","spread":true,"position":{"start":{"line":196,"column":1},"end":{"line":196,"column":1}},"children":[{"type":"paragraph","children":[{"type":"text","value":"distributed control on a subdomain ","position":{"start":{"line":196,"column":1},"end":{"line":196,"column":1}},"key":"n0IznxjW7s"},{"type":"inlineMath","value":"\\omega\\subset\\Omega","position":{"start":{"line":196,"column":1},"end":{"line":196,"column":1}},"html":"<span class=\"katex\"><span class=\"katex-mathml\"><math xmlns=\"http://www.w3.org/1998/Math/MathML\"><semantics><mrow><mi>ω</mi><mo>⊂</mo><mi mathvariant=\"normal\">Ω</mi></mrow><annotation encoding=\"application/x-tex\">\\omega\\subset\\Omega</annotation></semantics></math></span><span class=\"katex-html\" aria-hidden=\"true\"><span class=\"base\"><span class=\"strut\" style=\"height:0.5782em;vertical-align:-0.0391em;\"></span><span class=\"mord mathnormal\" style=\"margin-right:0.03588em;\">ω</span><span class=\"mspace\" style=\"margin-right:0.2778em;\"></span><span class=\"mrel\">⊂</span><span class=\"mspace\" style=\"margin-right:0.2778em;\"></span></span><span class=\"base\"><span class=\"strut\" style=\"height:0.6833em;\"></span><span class=\"mord\">Ω</span></span></span></span>","key":"S34EmHzPQF"}],"key":"q7XeiMgPea"}],"key":"ItzL8iH3fg"},{"type":"listItem","spread":true,"position":{"start":{"line":197,"column":1},"end":{"line":197,"column":1}},"children":[{"type":"paragraph","children":[{"type":"text","value":"boundary control on part of ","position":{"start":{"line":197,"column":1},"end":{"line":197,"column":1}},"key":"T6rgFTvNSR"},{"type":"inlineMath","value":"\\partial\\Omega","position":{"start":{"line":197,"column":1},"end":{"line":197,"column":1}},"html":"<span class=\"katex\"><span class=\"katex-mathml\"><math xmlns=\"http://www.w3.org/1998/Math/MathML\"><semantics><mrow><mi mathvariant=\"normal\">∂</mi><mi mathvariant=\"normal\">Ω</mi></mrow><annotation encoding=\"application/x-tex\">\\partial\\Omega</annotation></semantics></math></span><span class=\"katex-html\" aria-hidden=\"true\"><span class=\"base\"><span class=\"strut\" style=\"height:0.6944em;\"></span><span class=\"mord\" style=\"margin-right:0.05556em;\">∂</span><span class=\"mord\">Ω</span></span></span></span>","key":"lqTWIqw2Rh"}],"key":"ghOwvjoyuH"}],"key":"Qj7AR6WH9g"},{"type":"listItem","spread":true,"position":{"start":{"line":198,"column":1},"end":{"line":198,"column":1}},"children":[{"type":"paragraph","children":[{"type":"text","value":"initial-condition control in time-dependent models","position":{"start":{"line":198,"column":1},"end":{"line":198,"column":1}},"key":"eRRRu5u5yB"}],"key":"coTkVbJaV9"}],"key":"ar8Ek8NuYC"},{"type":"listItem","spread":true,"position":{"start":{"line":199,"column":1},"end":{"line":199,"column":1}},"children":[{"type":"paragraph","children":[{"type":"text","value":"parameter identification (inverse problems / data assimilation)","position":{"start":{"line":199,"column":1},"end":{"line":199,"column":1}},"key":"pS4mLsfGNm"}],"key":"zAC3axq511"}],"key":"hkdqOsDgUi"},{"type":"listItem","spread":true,"position":{"start":{"line":200,"column":1},"end":{"line":200,"column":1}},"children":[{"type":"paragraph","children":[{"type":"text","value":"alternative tracking norms (","position":{"start":{"line":200,"column":1},"end":{"line":200,"column":1}},"key":"PVCiExyNsP"},{"type":"inlineMath","value":"L^2","position":{"start":{"line":200,"column":1},"end":{"line":200,"column":1}},"html":"<span class=\"katex\"><span class=\"katex-mathml\"><math xmlns=\"http://www.w3.org/1998/Math/MathML\"><semantics><mrow><msup><mi>L</mi><mn>2</mn></msup></mrow><annotation encoding=\"application/x-tex\">L^2</annotation></semantics></math></span><span class=\"katex-html\" aria-hidden=\"true\"><span class=\"base\"><span class=\"strut\" style=\"height:0.8141em;\"></span><span class=\"mord\"><span class=\"mord mathnormal\">L</span><span class=\"msupsub\"><span class=\"vlist-t\"><span class=\"vlist-r\"><span class=\"vlist\" style=\"height:0.8141em;\"><span style=\"top:-3.063em;margin-right:0.05em;\"><span class=\"pstrut\" style=\"height:2.7em;\"></span><span class=\"sizing reset-size6 size3 mtight\"><span class=\"mord mtight\">2</span></span></span></span></span></span></span></span></span></span></span>","key":"k8lI9J9VaH"},{"type":"text","value":", ","position":{"start":{"line":200,"column":1},"end":{"line":200,"column":1}},"key":"T32rdTvPu3"},{"type":"inlineMath","value":"H^1","position":{"start":{"line":200,"column":1},"end":{"line":200,"column":1}},"html":"<span class=\"katex\"><span class=\"katex-mathml\"><math xmlns=\"http://www.w3.org/1998/Math/MathML\"><semantics><mrow><msup><mi>H</mi><mn>1</mn></msup></mrow><annotation encoding=\"application/x-tex\">H^1</annotation></semantics></math></span><span class=\"katex-html\" aria-hidden=\"true\"><span class=\"base\"><span class=\"strut\" style=\"height:0.8141em;\"></span><span class=\"mord\"><span class=\"mord mathnormal\" style=\"margin-right:0.08125em;\">H</span><span class=\"msupsub\"><span class=\"vlist-t\"><span class=\"vlist-r\"><span class=\"vlist\" style=\"height:0.8141em;\"><span style=\"top:-3.063em;margin-right:0.05em;\"><span class=\"pstrut\" style=\"height:2.7em;\"></span><span class=\"sizing reset-size6 size3 mtight\"><span class=\"mord mtight\">1</span></span></span></span></span></span></span></span></span></span></span>","key":"uubfCkxp0l"},{"type":"text","value":", weighted, mixed)","position":{"start":{"line":200,"column":1},"end":{"line":200,"column":1}},"key":"ZjbtZ7hhiE"}],"key":"leqW8GO0tK"}],"key":"I9qyUm2ox9"},{"type":"listItem","spread":true,"position":{"start":{"line":201,"column":1},"end":{"line":201,"column":1}},"children":[{"type":"paragraph","children":[{"type":"text","value":"alternative regularization (","position":{"start":{"line":201,"column":1},"end":{"line":201,"column":1}},"key":"Va5y8FIwDQ"},{"type":"inlineMath","value":"L^2","position":{"start":{"line":201,"column":1},"end":{"line":201,"column":1}},"html":"<span class=\"katex\"><span class=\"katex-mathml\"><math xmlns=\"http://www.w3.org/1998/Math/MathML\"><semantics><mrow><msup><mi>L</mi><mn>2</mn></msup></mrow><annotation encoding=\"application/x-tex\">L^2</annotation></semantics></math></span><span class=\"katex-html\" aria-hidden=\"true\"><span class=\"base\"><span class=\"strut\" style=\"height:0.8141em;\"></span><span class=\"mord\"><span class=\"mord mathnormal\">L</span><span class=\"msupsub\"><span class=\"vlist-t\"><span class=\"vlist-r\"><span class=\"vlist\" style=\"height:0.8141em;\"><span style=\"top:-3.063em;margin-right:0.05em;\"><span class=\"pstrut\" style=\"height:2.7em;\"></span><span class=\"sizing reset-size6 size3 mtight\"><span class=\"mord mtight\">2</span></span></span></span></span></span></span></span></span></span></span>","key":"leA53Kydl2"},{"type":"text","value":", ","position":{"start":{"line":201,"column":1},"end":{"line":201,"column":1}},"key":"RsGFNC7Tml"},{"type":"inlineMath","value":"H^1","position":{"start":{"line":201,"column":1},"end":{"line":201,"column":1}},"html":"<span class=\"katex\"><span class=\"katex-mathml\"><math xmlns=\"http://www.w3.org/1998/Math/MathML\"><semantics><mrow><msup><mi>H</mi><mn>1</mn></msup></mrow><annotation encoding=\"application/x-tex\">H^1</annotation></semantics></math></span><span class=\"katex-html\" aria-hidden=\"true\"><span class=\"base\"><span class=\"strut\" style=\"height:0.8141em;\"></span><span class=\"mord\"><span class=\"mord mathnormal\" style=\"margin-right:0.08125em;\">H</span><span class=\"msupsub\"><span class=\"vlist-t\"><span class=\"vlist-r\"><span class=\"vlist\" style=\"height:0.8141em;\"><span style=\"top:-3.063em;margin-right:0.05em;\"><span class=\"pstrut\" style=\"height:2.7em;\"></span><span class=\"sizing reset-size6 size3 mtight\"><span class=\"mord mtight\">1</span></span></span></span></span></span></span></span></span></span></span>","key":"JxLoUMZ5Il"},{"type":"text","value":", sparsity-promoting terms)","position":{"start":{"line":201,"column":1},"end":{"line":201,"column":1}},"key":"oreVExEp9K"}],"key":"uhEMsOXbvG"}],"key":"GtRGO2ZYuB"},{"type":"listItem","spread":true,"position":{"start":{"line":202,"column":1},"end":{"line":202,"column":1}},"children":[{"type":"paragraph","children":[{"type":"text","value":"pointwise state constraints","position":{"start":{"line":202,"column":1},"end":{"line":202,"column":1}},"key":"CXCznm3JHS"}],"key":"xn4PR5eYe1"}],"key":"gfgmkOPz0a"},{"type":"listItem","spread":true,"position":{"start":{"line":203,"column":1},"end":{"line":203,"column":1}},"children":[{"type":"paragraph","children":[{"type":"text","value":"robust / uncertainty-aware objectives","position":{"start":{"line":203,"column":1},"end":{"line":203,"column":1}},"key":"pXdXGCd7hl"}],"key":"p6U96k114F"}],"key":"Fd8cDcTy7x"}],"key":"wTNBuOTwrh"}],"key":"WeHyAwRXVy"}],"key":"Gg15ykwlds"},"references":{"cite":{"order":[],"data":{}}},"footer":{"navigation":{"prev":{"title":"Finite-Dimensional Analogy","url":"/finite-dim-analogy","group":"Codes"},"next":{"title":"KKT Conditions in Finite Dimensions","url":"/slides/slides02","group":"Slides"}}},"domain":"http://localhost:3000"}